[
  {
    "bazaarId": "41f3e518d3de4a4c90bd6654c023ed75",
    "hancoin": 300,
    "sellEndDate": "2025/04/20 09:56",
    "listingItems": [
      "A410PY",
      "B110K",
      "AFMQ",
      "ADOQ"
    ]
  },
  {
    "bazaarId": "4623dcd2c62043b0a4f1af8f6c300c47",
    "hancoin": 100,
    "sellEndDate": "2025/04/21 20:53",
    "listingItems": [
      "A4X9J",
      "A410PY",
      "A4C2M",
      "A4BWJ"
    ]
  },
  {
    "bazaarId": "f795d96a2b5247b29ac372770f718a6b",
    "hancoin": 500,
    "sellEndDate": "2025/04/19 16:14",
    "listingItems": [
      "A4198S"
    ]
  },
  {
    "bazaarId": "5d811d9537254797b05320e78f67a2c7",
    "hancoin": 600,
    "sellEndDate": "2025/04/20 19:30",
    "listingItems": [
      "A4198S"
    ]
  },
  {
    "bazaarId": "17c76bc936e7492c97b6c3502a1315be",
    "hancoin": 1000,
    "sellEndDate": "2025/04/24 04:33",
    "listingItems": [
      "A4198S"
    ]
  },
  {
    "bazaarId": "8c62af8afebf4998a4afa56e26e0d24f",
    "hancoin": 800,
    "sellEndDate": "2025/04/24 08:27",
    "listingItems": [
      "A4198S"
    ]
  },
  {
    "bazaarId": "468a7a6b599946db95d1271d14cbce89",
    "hancoin": 1000,
    "sellEndDate": "2025/04/19 18:23",
    "listingItems": [
      "P121991",
      "HD2198X",
      "LD2198Z"
    ]
  },
  {
    "bazaarId": "a3d2f9aecfa14332b97a80cb1bd59656",
    "hancoin": 4500,
    "sellEndDate": "2025/04/21 20:16",
    "listingItems": [
      "P126SP"
    ]
  },
  {
    "bazaarId": "cd1b7ba3e7744bfd8cf50eb231066389",
    "hancoin": 3800,
    "sellEndDate": "2025/04/26 12:04",
    "listingItems": [
      "P126SP"
    ]
  },
  {
    "bazaarId": "cdd37781a2854483bcc4bbc185edfe6e",
    "hancoin": 1000,
    "sellEndDate": "2025/04/21 18:43",
    "listingItems": [
      "B113T8",
      "LC2EN4",
      "P1213B9"
    ]
  },
  {
    "bazaarId": "e838d7d5edf1412ea4d5db28bf123a5a",
    "hancoin": 100,
    "sellEndDate": "2025/04/26 12:04",
    "listingItems": [
      "P1213B9"
    ]
  },
  {
    "bazaarId": "a554462490e94a63922e79007e06d258",
    "hancoin": 100,
    "sellEndDate": "2025/04/26 12:03",
    "listingItems": [
      "B118SI",
      "LC2ECI",
      "A3217N",
      "B324S"
    ]
  },
  {
    "bazaarId": "29abc795d940448dac07c4bd70bd422d",
    "hancoin": 500,
    "sellEndDate": "2025/04/22 03:55",
    "listingItems": [
      "B118SI",
      "A418XH",
      "P1213L4",
      "LD218FL"
    ]
  },
  {
    "bazaarId": "8fa50826fa1b469a82cb8c9fc90cb958",
    "hancoin": 100,
    "sellEndDate": "2025/04/22 11:09",
    "listingItems": [
      "A218XG",
      "LC2EIS",
      "B118SI",
      "B113T8"
    ]
  },
  {
    "bazaarId": "2a215265f4fc4db89cbe8d415a63552f",
    "hancoin": 300,
    "sellEndDate": "2025/04/22 20:49",
    "listingItems": [
      "HD118XL",
      "B118SI",
      "LD118SL",
      "P1118SN"
    ]
  },
  {
    "bazaarId": "f85e2456ebb74bcc83770964ce50aa74",
    "hancoin": 300,
    "sellEndDate": "2025/04/23 14:05",
    "listingItems": [
      "B118SI",
      "A118FC"
    ]
  },
  {
    "bazaarId": "123783a9c3ee4e03bf15a5c0317727ae",
    "hancoin": 100,
    "sellEndDate": "2025/04/23 17:07",
    "listingItems": [
      "B118SI"
    ]
  },
  {
    "bazaarId": "1d00f777f0104222a3e0b481f8ca0f94",
    "hancoin": 200,
    "sellEndDate": "2025/04/24 20:02",
    "listingItems": [
      "A418SG",
      "B118SI",
      "LD218SM",
      "P1218SO"
    ]
  },
  {
    "bazaarId": "78781db21fc14b5c84fa18598c1ccdd7",
    "hancoin": 200,
    "sellEndDate": "2025/04/24 20:02",
    "listingItems": [
      "A118SD",
      "A418SG",
      "B118SI",
      "P1218SO"
    ]
  },
  {
    "bazaarId": "6a3ce67c7b45469bb862033f165e3b61",
    "hancoin": 200,
    "sellEndDate": "2025/04/24 20:03",
    "listingItems": [
      "B118SI",
      "A418SG",
      "AA18FE",
      "B32182G"
    ]
  },
  {
    "bazaarId": "3c9c46e3c4a644ed9b0b87b57aac6fd5",
    "hancoin": 200,
    "sellEndDate": "2025/04/25 07:56",
    "listingItems": [
      "LD118FK",
      "A418XH",
      "B118SI"
    ]
  },
  {
    "bazaarId": "d19ee3b27a5947209112678c344878c1",
    "hancoin": 300,
    "sellEndDate": "2025/04/20 02:02",
    "listingItems": [
      "E418XK",
      "A418XH",
      "LD118XN",
      "P1118XP"
    ]
  },
  {
    "bazaarId": "192fe8db023f4c97b604e55ec364ce19",
    "hancoin": 500,
    "sellEndDate": "2025/04/20 17:29",
    "listingItems": [
      "HD118FI",
      "AE18FF",
      "A418XH",
      "A118FC"
    ]
  },
  {
    "bazaarId": "fd14d5f5de28485f995d23471d8f8d8a",
    "hancoin": 100,
    "sellEndDate": "2025/04/21 11:33",
    "listingItems": [
      "A418XH",
      "E41O5"
    ]
  },
  {
    "bazaarId": "e8f2a23b583c4daead7833e80270f75f",
    "hancoin": 200,
    "sellEndDate": "2025/04/21 11:45",
    "listingItems": [
      "AFNO",
      "E41O5",
      "E418XK",
      "A418XH"
    ]
  },
  {
    "bazaarId": "43193486b95347ca98147baf1e5d2a24",
    "hancoin": 100,
    "sellEndDate": "2025/04/22 11:10",
    "listingItems": [
      "A418XH",
      "LD218SM",
      "P1218XQ"
    ]
  },
  {
    "bazaarId": "4cff7007096d4772ba78813a4a70bdc4",
    "hancoin": 300,
    "sellEndDate": "2025/04/22 11:27",
    "listingItems": [
      "A418XH",
      "E11KM",
      "B3180",
      "AB2LS"
    ]
  },
  {
    "bazaarId": "47f9df70c7834346964806f5eb85592f",
    "hancoin": 200,
    "sellEndDate": "2025/04/22 11:23",
    "listingItems": [
      "AB2OZ",
      "E31ZU",
      "E21VF"
    ]
  },
  {
    "bazaarId": "c7c5846a19f44d87a0054a44a6a2c465",
    "hancoin": 100,
    "sellEndDate": "2025/04/21 11:30",
    "listingItems": [
      "P1118XP",
      "AA2KC",
      "AB2OZ"
    ]
  },
  {
    "bazaarId": "6e3ca8f129be4264851e1c790663c6e5",
    "hancoin": 1000,
    "sellEndDate": "2025/04/22 11:13",
    "listingItems": [
      "LC2DNK",
      "CT2UL",
      "B1CP"
    ]
  },
  {
    "bazaarId": "9d13f7710a6142c08da5ab0a4fe9af55",
    "hancoin": 400,
    "sellEndDate": "2025/04/20 20:34",
    "listingItems": [
      "CT2UL"
    ]
  },
  {
    "bazaarId": "b36501d0a8474fe0916c6ab57c345e2a",
    "hancoin": 1000,
    "sellEndDate": "2025/04/19 19:14",
    "listingItems": [
      "FA21KB"
    ]
  },
  {
    "bazaarId": "83f84e4c9570493499eb738284b39a82",
    "hancoin": 900,
    "sellEndDate": "2025/04/22 11:12",
    "listingItems": [
      "FA21KB"
    ]
  },
  {
    "bazaarId": "65df92c800b34261b298f02be14594b3",
    "hancoin": 600,
    "sellEndDate": "2025/04/20 00:53",
    "listingItems": [
      "A48DC"
    ]
  },
  {
    "bazaarId": "b960a14d2578442382adb9c237465d69",
    "hancoin": 500,
    "sellEndDate": "2025/04/22 11:11",
    "listingItems": [
      "A48DC"
    ]
  },
  {
    "bazaarId": "ae5f478f608345d9ac3a887375d7b29e",
    "hancoin": 4300,
    "sellEndDate": "2025/04/22 11:11",
    "listingItems": [
      "AD10D"
    ]
  },
  {
    "bazaarId": "91a32e07247e4a58b2a7a71a4075d8ec",
    "hancoin": 900,
    "sellEndDate": "2025/04/24 19:59",
    "listingItems": [
      "A418SG",
      "HD2XKY",
      "LD218SM",
      "HD218SK"
    ]
  },
  {
    "bazaarId": "494508606b0b47008641a135dc7b789f",
    "hancoin": 900,
    "sellEndDate": "2025/04/24 20:00",
    "listingItems": [
      "LD218SM",
      "HD218SK"
    ]
  },
  {
    "bazaarId": "15226dbe489d4128a887da914afc4076",
    "hancoin": 100,
    "sellEndDate": "2025/04/20 19:52",
    "listingItems": [
      "P1218XQ"
    ]
  },
  {
    "bazaarId": "bb8aac51d9df42ec8764b9b1eadf063b",
    "hancoin": 100,
    "sellEndDate": "2025/04/21 20:54",
    "listingItems": [
      "B113T8",
      "AEYIK",
      "CT110Q1",
      "A41149"
    ]
  },
  {
    "bazaarId": "a44ba4d7e4074bf38539eba616093524",
    "hancoin": 1600,
    "sellEndDate": "2025/04/23 16:52",
    "listingItems": [
      "LC2EKH",
      "B113T8",
      "AB12IZ"
    ]
  },
  {
    "bazaarId": "dfd8a978ddbb46b9bc5eb6f415132a45",
    "hancoin": 300,
    "sellEndDate": "2025/04/19 16:20",
    "listingItems": [
      "AA3C5",
      "A218XG",
      "P11347",
      "LC1CP9"
    ]
  },
  {
    "bazaarId": "a394ba252d7340dc947f29157389b8d7",
    "hancoin": 200,
    "sellEndDate": "2025/04/19 21:45",
    "listingItems": [
      "A218XG",
      "P1167W",
      "AA13T7",
      "A413KW"
    ]
  },
  {
    "bazaarId": "20a9f4e4dca64de9b2496e86bd98f2c9",
    "hancoin": 200,
    "sellEndDate": "2025/04/19 21:45",
    "listingItems": [
      "E31IU",
      "A218XG",
      "HD118B1",
      "LD1182J"
    ]
  },
  {
    "bazaarId": "c58c278564864968934c47f2b852fda8",
    "hancoin": 100,
    "sellEndDate": "2025/04/21 01:46",
    "listingItems": [
      "A41059",
      "A218XG"
    ]
  },
  {
    "bazaarId": "0eebd1a4d0694fe185937f51205cf14f",
    "hancoin": 100,
    "sellEndDate": "2025/04/21 01:47",
    "listingItems": [
      "A218XG",
      "A41059"
    ]
  },
  {
    "bazaarId": "21bc194bccc047d6bb015e8e100898e4",
    "hancoin": 100,
    "sellEndDate": "2025/04/21 14:42",
    "listingItems": [
      "A218XG",
      "HD118B1"
    ]
  },
  {
    "bazaarId": "8c7311d08ae44611bb310b0dc0d5013d",
    "hancoin": 300,
    "sellEndDate": "2025/04/21 14:46",
    "listingItems": [
      "A218XG",
      "HD118XL",
      "P1118XP",
      "P118DY"
    ]
  },
  {
    "bazaarId": "797f6ec24a5243e58ddf74aa1fe89720",
    "hancoin": 100,
    "sellEndDate": "2025/04/21 14:46",
    "listingItems": [
      "A218XG",
      "P1118XP"
    ]
  },
  {
    "bazaarId": "163e9db7a9d44c1baa1c02697ab861b0",
    "hancoin": 200,
    "sellEndDate": "2025/04/21 23:02",
    "listingItems": [
      "A218XG",
      "E11JP",
      "CT1HN",
      "E21R3"
    ]
  },
  {
    "bazaarId": "cda45ad0815c49928ca10b674c68c1d3",
    "hancoin": 200,
    "sellEndDate": "2025/04/23 17:45",
    "listingItems": [
      "E41TK",
      "E11JP",
      "A218XG",
      "LD1182J"
    ]
  },
  {
    "bazaarId": "dc1f7b9bb0154967b95b048ee243c4b1",
    "hancoin": 100,
    "sellEndDate": "2025/04/22 11:09",
    "listingItems": [
      "E418XK",
      "LC2EMM",
      "AA2ML",
      "A4BSH"
    ]
  },
  {
    "bazaarId": "d81b9c14caff4c50ac5b5eec4b8a90cc",
    "hancoin": 200,
    "sellEndDate": "2025/04/19 21:47",
    "listingItems": [
      "E418XK",
      "LC1ELI",
      "A15DY",
      "LD1198Y"
    ]
  },
  {
    "bazaarId": "d90bd9d5ab694617acbc47a2869e695b",
    "hancoin": 200,
    "sellEndDate": "2025/04/20 02:02",
    "listingItems": [
      "P1118XP",
      "E418XK"
    ]
  },
  {
    "bazaarId": "f8f41d3cc8034c6eb96d01236b821107",
    "hancoin": 300,
    "sellEndDate": "2025/04/20 14:03",
    "listingItems": [
      "HD112EK",
      "LD113TE",
      "E418XK"
    ]
  },
  {
    "bazaarId": "60caaa74404140259d90835e7bfe2c5e",
    "hancoin": 100,
    "sellEndDate": "2025/04/21 01:43",
    "listingItems": [
      "E418XK"
    ]
  },
  {
    "bazaarId": "7bfc1eda808041b59b53f94b692bf6ee",
    "hancoin": 400,
    "sellEndDate": "2025/04/21 11:39",
    "listingItems": [
      "AA2CJ",
      "E418XK",
      "A495Y",
      "P1153S"
    ]
  },
  {
    "bazaarId": "6c617015905f4664a963fc8d7ac6b303",
    "hancoin": 700,
    "sellEndDate": "2025/04/22 21:12",
    "listingItems": [
      "HD118FI",
      "CT1HE",
      "E418XK",
      "P1118SN"
    ]
  },
  {
    "bazaarId": "84f0daadaff5494babfa1c54eed8b037",
    "hancoin": 200,
    "sellEndDate": "2025/04/22 21:16",
    "listingItems": [
      "AA1AQ",
      "LC1DUO",
      "E418XK",
      "P1118SN"
    ]
  },
  {
    "bazaarId": "347701aaf8b94004bc4471b3a64f80ab",
    "hancoin": 100,
    "sellEndDate": "2025/04/23 23:47",
    "listingItems": [
      "P1155J",
      "CT1R4",
      "AE4FK",
      "E418XK"
    ]
  },
  {
    "bazaarId": "edee0f2b27d24ad79d29b20164a55d61",
    "hancoin": 300,
    "sellEndDate": "2025/04/24 21:22",
    "listingItems": [
      "E418XK"
    ]
  },
  {
    "bazaarId": "ebaef0667c344c3bbab2120e2fdc631d",
    "hancoin": 100,
    "sellEndDate": "2025/04/24 23:56",
    "listingItems": [
      "E418XK"
    ]
  },
  {
    "bazaarId": "6c199a2b80d94b439973f9419d91466d",
    "hancoin": 100,
    "sellEndDate": "2025/04/24 23:56",
    "listingItems": [
      "E418XK"
    ]
  },
  {
    "bazaarId": "a16c6a7c71e84651bf4842f0c01d9799",
    "hancoin": 100,
    "sellEndDate": "2025/04/25 23:29",
    "listingItems": [
      "E418XK"
    ]
  },
  {
    "bazaarId": "e62b04c47d8e49ae966e9e7a61c1b49f",
    "hancoin": 300,
    "sellEndDate": "2025/04/20 10:44",
    "listingItems": [
      "AAWUL",
      "AAZA0",
      "AAZSC",
      "AAYGY"
    ]
  },
  {
    "bazaarId": "463a22be177f4b43a2bf242b189454d6",
    "hancoin": 100,
    "sellEndDate": "2025/04/19 20:40",
    "listingItems": [
      "LD218FL",
      "A118SD",
      "A4X9J",
      "AA18FE"
    ]
  },
  {
    "bazaarId": "e363157662fe43dc8c6a14d693813841",
    "hancoin": 200,
    "sellEndDate": "2025/04/19 21:46",
    "listingItems": [
      "B31182F",
      "AA18FE",
      "P1118XP",
      "A1198R"
    ]
  },
  {
    "bazaarId": "689945f960234266b43e08cacda3c3a2",
    "hancoin": 400,
    "sellEndDate": "2025/04/22 21:43",
    "listingItems": [
      "P1111LR",
      "HD112ZB",
      "AA18FE",
      "LD118SL"
    ]
  },
  {
    "bazaarId": "9b56dacc62a44ec9915ee89384b23f89",
    "hancoin": 200,
    "sellEndDate": "2025/04/24 20:18",
    "listingItems": [
      "B112U9",
      "E315D",
      "AA18FE",
      "AB3NX"
    ]
  },
  {
    "bazaarId": "352b7d7a9a9345879d80dab8b86cdd9f",
    "hancoin": 200,
    "sellEndDate": "2025/04/25 08:01",
    "listingItems": [
      "E41N0",
      "AA18FE",
      "AB18AZ",
      "A1198R"
    ]
  },
  {
    "bazaarId": "b867bda175c3416487fc832a65ab81f4",
    "hancoin": 100,
    "sellEndDate": "2025/04/26 09:08",
    "listingItems": [
      "LC1A73",
      "A48RI",
      "AA18FE",
      "B118FG"
    ]
  },
  {
    "bazaarId": "1e49b869671c4ff68d74ee8dbc3d30b4",
    "hancoin": 300,
    "sellEndDate": "2025/04/26 10:34",
    "listingItems": [
      "P1118XP",
      "B31182F",
      "AA18FE",
      "AB18AZ"
    ]
  },
  {
    "bazaarId": "2b213122811949f3a1d2b99e1b71fd4a",
    "hancoin": 100,
    "sellEndDate": "2025/04/19 16:23",
    "listingItems": [
      "AB18AZ"
    ]
  },
  {
    "bazaarId": "6a41a67b9a294c4dab9a52d681dac6ee",
    "hancoin": 200,
    "sellEndDate": "2025/04/19 21:47",
    "listingItems": [
      "ABGX",
      "P1118XP",
      "LD118SL",
      "AB18AZ"
    ]
  },
  {
    "bazaarId": "9f2560cb88a344eaaf11f1f62bd3253d",
    "hancoin": 300,
    "sellEndDate": "2025/04/21 20:38",
    "listingItems": [
      "AA12EF",
      "AB18AZ",
      "CT1R4",
      "LD118XN"
    ]
  },
  {
    "bazaarId": "996e2e51bfa742b7ac09486460b7b1d9",
    "hancoin": 100,
    "sellEndDate": "2025/04/25 23:33",
    "listingItems": [
      "AB18AZ"
    ]
  },
  {
    "bazaarId": "02d9788c316f461098ebe02d93f00ca9",
    "hancoin": 100,
    "sellEndDate": "2025/04/22 09:23",
    "listingItems": [
      "P11803",
      "AA12U8",
      "A25SA"
    ]
  },
  {
    "bazaarId": "cf4c208e3ed84ec8be5984c7f19f1661",
    "hancoin": 300,
    "sellEndDate": "2025/04/23 01:08",
    "listingItems": [
      "E319O",
      "A455Q",
      "AA12U8",
      "AD12J0"
    ]
  },
  {
    "bazaarId": "b0aef0bba9694c57aa054a91a611181d",
    "hancoin": 1500,
    "sellEndDate": "2025/04/24 17:56",
    "listingItems": [
      "B1UY",
      "E112ZA",
      "AA12U8",
      "B212UA"
    ]
  },
  {
    "bazaarId": "8606f108355e40b1bd193eeff5b5913a",
    "hancoin": 300,
    "sellEndDate": "2025/04/21 23:54",
    "listingItems": [
      "A44W1",
      "AAW45",
      "E41ZT"
    ]
  },
  {
    "bazaarId": "a29311af316243a8bcab94f4f3278b3a",
    "hancoin": 300,
    "sellEndDate": "2025/04/26 09:11",
    "listingItems": [
      "P1158J",
      "AF1A9",
      "A44W1",
      "CT1DN"
    ]
  },
  {
    "bazaarId": "78724123ee5d40849caf9c45e3c9c819",
    "hancoin": 200,
    "sellEndDate": "2025/04/26 09:10",
    "listingItems": [
      "E1Z2",
      "A141O",
      "AA1MR",
      "P118K3"
    ]
  },
  {
    "bazaarId": "da4f94e0e3ab480fb0adea4013d53d47",
    "hancoin": 200,
    "sellEndDate": "2025/04/21 23:01",
    "listingItems": [
      "E41KU",
      "E1Z2",
      "E11JP",
      "P1158J"
    ]
  },
  {
    "bazaarId": "7fb3634166f746aea80d6dad558b69e4",
    "hancoin": 100,
    "sellEndDate": "2025/04/26 09:09",
    "listingItems": [
      "E41BL",
      "AEFE",
      "A130Y",
      "A45CD"
    ]
  },
  {
    "bazaarId": "ec9fc7b7043a414b8e13725ab0cba801",
    "hancoin": 100,
    "sellEndDate": "2025/04/26 09:09",
    "listingItems": [
      "A23AL",
      "AAMI",
      "CT1EJ",
      "AE1KH"
    ]
  },
  {
    "bazaarId": "81fcc80d099b4d1fb0f3eb6657a9d18c",
    "hancoin": 200,
    "sellEndDate": "2025/04/20 19:21",
    "listingItems": [
      "LD118FK",
      "AE18FF",
      "B118FG",
      "A118FC"
    ]
  },
  {
    "bazaarId": "905e8f6efaf742379ac4d313a24142b1",
    "hancoin": 100,
    "sellEndDate": "2025/04/26 09:07",
    "listingItems": [
      "E1N9",
      "A12WO",
      "E21LQ",
      "B118FG"
    ]
  },
  {
    "bazaarId": "3b0b5a60aa814e0bb23bd7e03fcbe643",
    "hancoin": 100,
    "sellEndDate": "2025/04/26 09:07",
    "listingItems": [
      "A229J",
      "A44S4",
      "LC1CS6",
      "B118FG"
    ]
  },
  {
    "bazaarId": "e9eafdf6835d497192236091b74b1a0e",
    "hancoin": 500,
    "sellEndDate": "2025/04/22 09:06",
    "listingItems": [
      "A311YQ",
      "A118FC",
      "E21LQ",
      "LC1EEP"
    ]
  },
  {
    "bazaarId": "cc05f8c38ce441b28eacc5f64d8dc2ba",
    "hancoin": 500,
    "sellEndDate": "2025/04/22 09:07",
    "listingItems": [
      "LD118FK",
      "CT1GB",
      "E41BQ",
      "HD118FI"
    ]
  },
  {
    "bazaarId": "9c2dd2276eff40baa05bfe324ce31e78",
    "hancoin": 100,
    "sellEndDate": "2025/04/24 06:24",
    "listingItems": [
      "E41BQ"
    ]
  },
  {
    "bazaarId": "ef106bacaf3342dcb9c37435fa594a73",
    "hancoin": 900,
    "sellEndDate": "2025/04/24 20:01",
    "listingItems": [
      "E41BQ",
      "A2XKS"
    ]
  },
  {
    "bazaarId": "2eea734659694becb9bdb8f48c3fb08e",
    "hancoin": 100,
    "sellEndDate": "2025/04/25 07:31",
    "listingItems": [
      "E41BQ"
    ]
  },
  {
    "bazaarId": "6a7c16c48a34493c9728a94397dc318a",
    "hancoin": 800,
    "sellEndDate": "2025/04/24 04:53",
    "listingItems": [
      "A418FD",
      "HD113KZ",
      "P1113L3",
      "A118FC"
    ]
  },
  {
    "bazaarId": "1c9c78f761594c18845344f5b3ffd5b1",
    "hancoin": 200,
    "sellEndDate": "2025/04/24 17:52",
    "listingItems": [
      "A118FC"
    ]
  },
  {
    "bazaarId": "f74a7d80d2bf4a2b8486016129373ecc",
    "hancoin": 1800,
    "sellEndDate": "2025/04/24 20:03",
    "listingItems": [
      "A118FC",
      "A118SD",
      "A418FD",
      "A211LI"
    ]
  },
  {
    "bazaarId": "9851889c35e24d259d0bb1b0b23f6834",
    "hancoin": 200,
    "sellEndDate": "2025/04/26 07:53",
    "listingItems": [
      "B114Z",
      "B2GC",
      "A4AQI"
    ]
  },
  {
    "bazaarId": "67cbe743ce17425b86a4d589325f998c",
    "hancoin": 200,
    "sellEndDate": "2025/04/26 07:52",
    "listingItems": [
      "A4B4L",
      "ADOQ",
      "AFW8"
    ]
  },
  {
    "bazaarId": "5e16e73b61c1422b822c7beb3164ae19",
    "hancoin": 7000,
    "sellEndDate": "2025/04/20 07:39",
    "listingItems": [
      "AA35S"
    ]
  },
  {
    "bazaarId": "53b40619de504a4dba79c29ca705d76b",
    "hancoin": 1000,
    "sellEndDate": "2025/04/25 19:49",
    "listingItems": [
      "P1118XP",
      "LD118SL",
      "LD118XN",
      "AB376"
    ]
  },
  {
    "bazaarId": "7397b35121c84df891414b3bf615cde9",
    "hancoin": 200,
    "sellEndDate": "2025/04/20 19:24",
    "listingItems": [
      "B32182G",
      "ADTRX",
      "A4B9R",
      "CT213B2"
    ]
  },
  {
    "bazaarId": "b417f06ec75d40e5ad4a91d89d22e43c",
    "hancoin": 1500,
    "sellEndDate": "2025/04/24 20:00",
    "listingItems": [
      "HD218FJ",
      "A44ZX",
      "AE1OB",
      "P1268A"
    ]
  },
  {
    "bazaarId": "189b8555943b40a1a9aba074ae02a3da",
    "hancoin": 200,
    "sellEndDate": "2025/04/20 03:33",
    "listingItems": [
      "A12XC",
      "AEKA",
      "LC1ELQ",
      "E1132"
    ]
  },
  {
    "bazaarId": "aecc4090f2164b2388052e04a6d62692",
    "hancoin": 7500,
    "sellEndDate": "2025/04/20 02:58",
    "listingItems": [
      "E421I"
    ]
  },
  {
    "bazaarId": "36f7f06b66064770a9053e7c31016981",
    "hancoin": 7500,
    "sellEndDate": "2025/04/20 22:11",
    "listingItems": [
      "E421I"
    ]
  },
  {
    "bazaarId": "5ae627035f0a46ae81b37da3e8d6de52",
    "hancoin": 7000,
    "sellEndDate": "2025/04/21 19:09",
    "listingItems": [
      "E421I"
    ]
  },
  {
    "bazaarId": "c26f257ff03244f8bd6670d8dcb67843",
    "hancoin": 6500,
    "sellEndDate": "2025/04/22 05:07",
    "listingItems": [
      "E421I"
    ]
  },
  {
    "bazaarId": "1dfd5ff86371461ea071b1d56396c6a9",
    "hancoin": 1500,
    "sellEndDate": "2025/04/21 16:20",
    "listingItems": [
      "A418FD"
    ]
  },
  {
    "bazaarId": "97f9dda80edf479bbe414dab1bdb47e6",
    "hancoin": 800,
    "sellEndDate": "2025/04/23 14:28",
    "listingItems": [
      "A418FD"
    ]
  },
  {
    "bazaarId": "b73833da16954f01813b31ad72de9daf",
    "hancoin": 600,
    "sellEndDate": "2025/04/25 16:35",
    "listingItems": [
      "A418FD"
    ]
  },
  {
    "bazaarId": "80fefc36dc204a41a39006564a99737e",
    "hancoin": 600,
    "sellEndDate": "2025/04/25 18:39",
    "listingItems": [
      "A418FD"
    ]
  },
  {
    "bazaarId": "1d8b7f4ac2764b3cbaac1c87dd333203",
    "hancoin": 800,
    "sellEndDate": "2025/04/26 04:57",
    "listingItems": [
      "A418FD",
      "HD113KZ",
      "HD118XL",
      "LD118FK"
    ]
  },
  {
    "bazaarId": "efff039b92364b5b855a22d0e83f54fc",
    "hancoin": 1500,
    "sellEndDate": "2025/04/21 23:56",
    "listingItems": [
      "A1ZHM"
    ]
  },
  {
    "bazaarId": "1a954a52cf6a45b68d0076d5ef77ebfa",
    "hancoin": 1000,
    "sellEndDate": "2025/04/26 04:28",
    "listingItems": [
      "A1ZHM"
    ]
  },
  {
    "bazaarId": "d2124f12b4524c5883880e962c8117f1",
    "hancoin": 200,
    "sellEndDate": "2025/04/19 18:11",
    "listingItems": [
      "HD118XL",
      "A418SG"
    ]
  },
  {
    "bazaarId": "ed7a094ff53c44d094329e1facda82da",
    "hancoin": 1500,
    "sellEndDate": "2025/04/19 19:21",
    "listingItems": [
      "AA11GD",
      "A418SG",
      "LD211GI",
      "HD218FJ"
    ]
  },
  {
    "bazaarId": "b292bf75bddb46b3876b4bc30a7137b4",
    "hancoin": 300,
    "sellEndDate": "2025/04/22 03:55",
    "listingItems": [
      "AA182D",
      "AE18FF",
      "A418SG",
      "HD218XM"
    ]
  },
  {
    "bazaarId": "62a46d90f7584c07ab96f51531cd0e16",
    "hancoin": 600,
    "sellEndDate": "2025/04/22 21:10",
    "listingItems": [
      "HD118XL",
      "A418SG",
      "A3118SE"
    ]
  },
  {
    "bazaarId": "b341cdcec4464c91ba1353cec3e26e14",
    "hancoin": 600,
    "sellEndDate": "2025/04/22 21:10",
    "listingItems": [
      "HD118XL",
      "A418SG",
      "A3118SE"
    ]
  },
  {
    "bazaarId": "cc5da6db0ab341b1afb8803d9aab9cf8",
    "hancoin": 600,
    "sellEndDate": "2025/04/22 21:11",
    "listingItems": [
      "HD118XL",
      "A418SG",
      "A3118SE"
    ]
  },
  {
    "bazaarId": "3cda298fc1ff4bfe8462efa3e6fea7f3",
    "hancoin": 900,
    "sellEndDate": "2025/04/23 01:09",
    "listingItems": [
      "HD118XL",
      "A418SG",
      "E228Q",
      "A255N"
    ]
  },
  {
    "bazaarId": "59c94d16ff45470d8690eef29368fe8a",
    "hancoin": 100,
    "sellEndDate": "2025/04/24 19:48",
    "listingItems": [
      "HD218XM",
      "A418SG",
      "AE18FF"
    ]
  },
  {
    "bazaarId": "b9559a03374a43d2a54963c6aef29090",
    "hancoin": 100,
    "sellEndDate": "2025/04/24 20:34",
    "listingItems": [
      "A418SG"
    ]
  },
  {
    "bazaarId": "1df4501910ec4087819ec67425cb4174",
    "hancoin": 6000,
    "sellEndDate": "2025/04/22 13:59",
    "listingItems": [
      "HD118XL",
      "AE18FF",
      "E118XJ"
    ]
  },
  {
    "bazaarId": "d914ecbc32b2457f8c29e7820678340d",
    "hancoin": 200,
    "sellEndDate": "2025/04/25 07:51",
    "listingItems": [
      "AA198T",
      "AE18FF",
      "LD118B3"
    ]
  },
  {
    "bazaarId": "ec35a9f627fb44699b148d8ce76017ff",
    "hancoin": 300,
    "sellEndDate": "2025/04/26 00:42",
    "listingItems": [
      "LD118B3",
      "AE18FF",
      "HD118XL"
    ]
  },
  {
    "bazaarId": "2cc36459a03a43098125ace498cfe21e",
    "hancoin": 100,
    "sellEndDate": "2025/04/22 22:12",
    "listingItems": [
      "HD218XM",
      "CT2J2",
      "AA3N7"
    ]
  },
  {
    "bazaarId": "93ebef42dba844aaa029293207c5c656",
    "hancoin": 100,
    "sellEndDate": "2025/04/24 17:53",
    "listingItems": [
      "P1213L4"
    ]
  },
  {
    "bazaarId": "20a8f79f0480445284e641460b4b3156",
    "hancoin": 900,
    "sellEndDate": "2025/04/20 03:54",
    "listingItems": [
      "HC2TS1"
    ]
  },
  {
    "bazaarId": "bceb579572fc407980f41ed5b05624dc",
    "hancoin": 800,
    "sellEndDate": "2025/04/19 19:10",
    "listingItems": [
      "CT2TQ",
      "CT2LV",
      "P124QV",
      "A113AY"
    ]
  },
  {
    "bazaarId": "a9e1c0e38be44682aa420d95e24d3b3e",
    "hancoin": 1800,
    "sellEndDate": "2025/04/20 03:54",
    "listingItems": [
      "A412U7",
      "A113AY",
      "A321KR",
      "A4CR3"
    ]
  },
  {
    "bazaarId": "63ee3f0e4b3243a5b3a522cd4c6cc1b0",
    "hancoin": 500,
    "sellEndDate": "2025/04/23 19:50",
    "listingItems": [
      "B22SE",
      "A4ABO",
      "A321KR",
      "P123TE"
    ]
  },
  {
    "bazaarId": "f0b661114dde4b9a99f546efcfa7840e",
    "hancoin": 300,
    "sellEndDate": "2025/04/19 14:15",
    "listingItems": [
      "A412U7"
    ]
  },
  {
    "bazaarId": "180cdd3391ac42c08937fed5165f5b09",
    "hancoin": 1500,
    "sellEndDate": "2025/04/19 19:23",
    "listingItems": [
      "CT2TQ",
      "A118SD",
      "A412U7",
      "AAZHO"
    ]
  },
  {
    "bazaarId": "e7c26979d46943d09b7158a465209160",
    "hancoin": 2000,
    "sellEndDate": "2025/04/20 01:57",
    "listingItems": [
      "A412U7",
      "AAZHO",
      "A4Z8N",
      "P116F1"
    ]
  },
  {
    "bazaarId": "a170d0ef5244476884fa69579b37e388",
    "hancoin": 1200,
    "sellEndDate": "2025/04/20 01:59",
    "listingItems": [
      "AAZHO",
      "E411X0",
      "E1Z8Q",
      "A412U7"
    ]
  },
  {
    "bazaarId": "5a0cf9c8d59144a08910fa272aa5f9f7",
    "hancoin": 100,
    "sellEndDate": "2025/04/20 16:18",
    "listingItems": [
      "A4CR3"
    ]
  },
  {
    "bazaarId": "df9f055818ee4aad960670243a110b39",
    "hancoin": 100,
    "sellEndDate": "2025/04/24 08:05",
    "listingItems": [
      "A4CR3"
    ]
  },
  {
    "bazaarId": "17ff7acab7cf40fda5e5bba208826e80",
    "hancoin": 200,
    "sellEndDate": "2025/04/19 22:42",
    "listingItems": [
      "AFCJ",
      "B1UY",
      "A2TRU",
      "E3201"
    ]
  },
  {
    "bazaarId": "1877c75260d244e3914c3d6484bb1c5e",
    "hancoin": 1800,
    "sellEndDate": "2025/04/20 03:53",
    "listingItems": [
      "E21TI",
      "B32E0",
      "LC2DX9",
      "B1UY"
    ]
  },
  {
    "bazaarId": "10aae6e79e6d4e43be1aebb87fff465a",
    "hancoin": 1800,
    "sellEndDate": "2025/04/20 03:53",
    "listingItems": [
      "AF19Q",
      "E2197",
      "A46EL",
      "B1UO"
    ]
  },
  {
    "bazaarId": "5bbe1a1f944248fbade51e5d591a479f",
    "hancoin": 1500,
    "sellEndDate": "2025/04/20 03:52",
    "listingItems": [
      "A4182C"
    ]
  },
  {
    "bazaarId": "7a2bf3d25c2c4c7a84e1c95b64a02707",
    "hancoin": 800,
    "sellEndDate": "2025/04/19 14:05",
    "listingItems": [
      "B1ML"
    ]
  },
  {
    "bazaarId": "16e1d0266a6441ec9e60717c760ae300",
    "hancoin": 1200,
    "sellEndDate": "2025/04/20 03:51",
    "listingItems": [
      "B1ML"
    ]
  },
  {
    "bazaarId": "ce1dba61a3e94e70a916805276bb8d89",
    "hancoin": 800,
    "sellEndDate": "2025/04/22 14:26",
    "listingItems": [
      "B1ML"
    ]
  },
  {
    "bazaarId": "ded78195a5ae4da0bd873ad27cd6ca5b",
    "hancoin": 2000,
    "sellEndDate": "2025/04/23 16:49",
    "listingItems": [
      "A3213KV",
      "CT2JW",
      "AA2L2",
      "B1ML"
    ]
  },
  {
    "bazaarId": "029c1d1212cf45ac9602e8e8b9a9b273",
    "hancoin": 8000,
    "sellEndDate": "2025/04/25 01:23",
    "listingItems": [
      "E118XJ"
    ]
  },
  {
    "bazaarId": "dbc21593322f496fae954ca05dfe7ef7",
    "hancoin": 700,
    "sellEndDate": "2025/04/22 08:41",
    "listingItems": [
      "AAZ8O"
    ]
  },
  {
    "bazaarId": "2b089c1ad05f485889c0586cf5b6a3b2",
    "hancoin": 2000,
    "sellEndDate": "2025/04/23 16:50",
    "listingItems": [
      "A3213KV",
      "AAZ8O",
      "A322FU",
      "P12YO5"
    ]
  },
  {
    "bazaarId": "a51b64445bc44401a7ba0db7d7d7d092",
    "hancoin": 600,
    "sellEndDate": "2025/04/26 01:41",
    "listingItems": [
      "AAZ8O"
    ]
  },
  {
    "bazaarId": "4d5db84629c943e8afeb3c2803bee933",
    "hancoin": 2500,
    "sellEndDate": "2025/04/26 01:41",
    "listingItems": [
      "A110XQ",
      "LD112J3"
    ]
  },
  {
    "bazaarId": "c6af5bd9e77d4b0caeae43ae931f7d8b",
    "hancoin": 300,
    "sellEndDate": "2025/04/20 00:52",
    "listingItems": [
      "A14HH"
    ]
  },
  {
    "bazaarId": "6bddf728830748bba1b3b3e64c1c97f7",
    "hancoin": 200,
    "sellEndDate": "2025/04/26 00:32",
    "listingItems": [
      "AF1G8",
      "P1189J",
      "AA3S5",
      "AA11WX"
    ]
  },
  {
    "bazaarId": "9fe83893a33c4727b37c5f20f478282d",
    "hancoin": 100,
    "sellEndDate": "2025/04/24 21:27",
    "listingItems": [
      "AA11WX"
    ]
  },
  {
    "bazaarId": "6c80ea6021ad4ba3a99b33602b9172ca",
    "hancoin": 300,
    "sellEndDate": "2025/04/25 19:38",
    "listingItems": [
      "AA11WX"
    ]
  },
  {
    "bazaarId": "145563be9ee34532ad637c6a0e4b1855",
    "hancoin": 200,
    "sellEndDate": "2025/04/25 11:48",
    "listingItems": [
      "AF1JI",
      "A23TH",
      "B2392",
      "LC2ELB"
    ]
  },
  {
    "bazaarId": "fbb8c857399647b9a66afca01902a4ab",
    "hancoin": 4700,
    "sellEndDate": "2025/04/19 17:39",
    "listingItems": [
      "A113T5"
    ]
  },
  {
    "bazaarId": "48dff7a615ff409c9d4cadb22fcb4d7e",
    "hancoin": 6000,
    "sellEndDate": "2025/04/24 22:48",
    "listingItems": [
      "A113T5"
    ]
  },
  {
    "bazaarId": "36d27e84ce38401e8a58bf216ae397e7",
    "hancoin": 1800,
    "sellEndDate": "2025/04/19 18:11",
    "listingItems": [
      "A15HS",
      "AE3VR",
      "E41Z8",
      "AF18XI"
    ]
  },
  {
    "bazaarId": "42754cd2a61c4c8bba40c1890f8beba4",
    "hancoin": 2000,
    "sellEndDate": "2025/04/19 19:23",
    "listingItems": [
      "AF18XI",
      "AB440",
      "AA3LL",
      "HD118FI"
    ]
  },
  {
    "bazaarId": "01e488399fd84221aaca5a61cb97bc45",
    "hancoin": 1500,
    "sellEndDate": "2025/04/24 17:47",
    "listingItems": [
      "AF18XI"
    ]
  },
  {
    "bazaarId": "f70b0334fa7f4522992fabda13dfd7f4",
    "hancoin": 700,
    "sellEndDate": "2025/04/22 23:07",
    "listingItems": [
      "E110XV"
    ]
  },
  {
    "bazaarId": "23c03274bb804769bdac8dc4874dfa4a",
    "hancoin": 3200,
    "sellEndDate": "2025/04/19 19:37",
    "listingItems": [
      "LD212J4",
      "CT2TW",
      "E21SE",
      "AA18AY"
    ]
  },
  {
    "bazaarId": "091f670e57b945cd955e0d23b95b295a",
    "hancoin": 2000,
    "sellEndDate": "2025/04/25 19:36",
    "listingItems": [
      "AA18AY"
    ]
  },
  {
    "bazaarId": "d21111f6f85d4983acce2b3300e93aee",
    "hancoin": 1500,
    "sellEndDate": "2025/04/21 23:55",
    "listingItems": [
      "B1ZW7"
    ]
  },
  {
    "bazaarId": "fcd0c4c30a1c4774bfc3d15fff4ee9a0",
    "hancoin": 3500,
    "sellEndDate": "2025/04/25 19:35",
    "listingItems": [
      "B1ZW7"
    ]
  },
  {
    "bazaarId": "a090ba06a6b64922aba9a40335ce3770",
    "hancoin": 2000,
    "sellEndDate": "2025/04/19 19:12",
    "listingItems": [
      "B2114C",
      "HD210Q6",
      "AD10Q0",
      "A321YF"
    ]
  },
  {
    "bazaarId": "13bf4727949f4ef1b66e93d1ddf71af0",
    "hancoin": 1500,
    "sellEndDate": "2025/04/21 23:55",
    "listingItems": [
      "B2114C"
    ]
  },
  {
    "bazaarId": "346ca1a26eaa446da326f4480c912582",
    "hancoin": 1500,
    "sellEndDate": "2025/04/21 23:54",
    "listingItems": [
      "HD2YIO"
    ]
  },
  {
    "bazaarId": "9de105d4910949c993e37da5e8ad4cbe",
    "hancoin": 6000,
    "sellEndDate": "2025/04/22 19:10",
    "listingItems": [
      "AA18SH"
    ]
  },
  {
    "bazaarId": "e5186f3ea1954c08b46fd2a8630893ea",
    "hancoin": 5000,
    "sellEndDate": "2025/04/24 20:51",
    "listingItems": [
      "AA18SH"
    ]
  },
  {
    "bazaarId": "35cce591fe2f4e34b4868a4e46fd98e6",
    "hancoin": 1500,
    "sellEndDate": "2025/04/21 18:28",
    "listingItems": [
      "E312EJ"
    ]
  },
  {
    "bazaarId": "8f6c18efc45543f3badb636f6b32c1ed",
    "hancoin": 3800,
    "sellEndDate": "2025/04/19 19:32",
    "listingItems": [
      "E1Y79",
      "LD212ZE",
      "A211LI",
      "A3211GB"
    ]
  },
  {
    "bazaarId": "2459cf21397347929d76d8c1d795fb90",
    "hancoin": 1000,
    "sellEndDate": "2025/04/22 19:09",
    "listingItems": [
      "A211LI"
    ]
  },
  {
    "bazaarId": "3293a0a669ec4462946936281d5c6071",
    "hancoin": 1800,
    "sellEndDate": "2025/04/21 20:17",
    "listingItems": [
      "A11058"
    ]
  },
  {
    "bazaarId": "4b0d15a6b954418da07e40d5090654be",
    "hancoin": 1500,
    "sellEndDate": "2025/04/25 18:24",
    "listingItems": [
      "A11058"
    ]
  },
  {
    "bazaarId": "7a34044cf8f44bc693c878f08041f9cc",
    "hancoin": 1500,
    "sellEndDate": "2025/04/25 18:24",
    "listingItems": [
      "A11058"
    ]
  },
  {
    "bazaarId": "48207fbf6f634cffbe43875fe15d97b3",
    "hancoin": 2200,
    "sellEndDate": "2025/04/20 21:39",
    "listingItems": [
      "AFSB",
      "P11YO4",
      "B212UA"
    ]
  },
  {
    "bazaarId": "d5b0171428dc4fd3bb0821f84dd620ea",
    "hancoin": 1400,
    "sellEndDate": "2025/04/21 18:27",
    "listingItems": [
      "B212UA"
    ]
  },
  {
    "bazaarId": "f5ca5f690a78489480bc4ed68cb817e7",
    "hancoin": 1400,
    "sellEndDate": "2025/04/21 18:27",
    "listingItems": [
      "B212UA"
    ]
  },
  {
    "bazaarId": "1ddb46d7ef3b4072b7972516530dd034",
    "hancoin": 7000,
    "sellEndDate": "2025/04/21 23:39",
    "listingItems": [
      "A32XXD"
    ]
  },
  {
    "bazaarId": "fdf3b666d7b4451e8706c18ca31d215e",
    "hancoin": 12000,
    "sellEndDate": "2025/04/19 22:53",
    "listingItems": [
      "AFYXX"
    ]
  },
  {
    "bazaarId": "5cca3c6d787c4e38aea8c7a555baa4a4",
    "hancoin": 12000,
    "sellEndDate": "2025/04/21 07:50",
    "listingItems": [
      "AEYO0"
    ]
  },
  {
    "bazaarId": "ed01941b372b41c5bc9bc57f0b8ff7ff",
    "hancoin": 7000,
    "sellEndDate": "2025/04/21 23:39",
    "listingItems": [
      "AEYO0"
    ]
  },
  {
    "bazaarId": "1578c5a4d5824a9e88f5ae0736cd0578",
    "hancoin": 7000,
    "sellEndDate": "2025/04/21 23:38",
    "listingItems": [
      "P12Y7E"
    ]
  },
  {
    "bazaarId": "fca95620083a44448d07524ccf0bd40a",
    "hancoin": 100,
    "sellEndDate": "2025/04/25 23:29",
    "listingItems": [
      "E41TK"
    ]
  },
  {
    "bazaarId": "81851aec2f4e4910a660dd6a82364801",
    "hancoin": 100,
    "sellEndDate": "2025/04/25 23:29",
    "listingItems": [
      "E11MS"
    ]
  },
  {
    "bazaarId": "508da092a71a468388c56d4a1bf9cac8",
    "hancoin": 200,
    "sellEndDate": "2025/04/19 21:14",
    "listingItems": [
      "B1118"
    ]
  },
  {
    "bazaarId": "09b5dff9a4004154a696d371deddbec8",
    "hancoin": 700,
    "sellEndDate": "2025/04/20 00:41",
    "listingItems": [
      "B1118",
      "A311UD",
      "E21KU",
      "E31Y9"
    ]
  },
  {
    "bazaarId": "5ed61ed16fe14384a7697560858790d9",
    "hancoin": 800,
    "sellEndDate": "2025/04/20 02:58",
    "listingItems": [
      "B1118",
      "E31Y9",
      "P1166B",
      "LC1E9C"
    ]
  },
  {
    "bazaarId": "4a1a1e444fc54b85b2382f8dc5f838ea",
    "hancoin": 1500,
    "sellEndDate": "2025/04/25 22:26",
    "listingItems": [
      "E41HN",
      "E31ND",
      "B1118",
      "B2YB"
    ]
  },
  {
    "bazaarId": "27bb8d79e14043e38eb759eca89e7bdf",
    "hancoin": 900,
    "sellEndDate": "2025/04/19 16:23",
    "listingItems": [
      "E41HN"
    ]
  },
  {
    "bazaarId": "7549f0a4bf4f4056a627607dbe783627",
    "hancoin": 500,
    "sellEndDate": "2025/04/24 21:33",
    "listingItems": [
      "B2YB"
    ]
  },
  {
    "bazaarId": "c3358b45159840c68785e06223fc8f5e",
    "hancoin": 100,
    "sellEndDate": "2025/04/21 01:52",
    "listingItems": [
      "E2114D",
      "E41Y9",
      "AA2BH",
      "AA10PZ"
    ]
  },
  {
    "bazaarId": "896749749d474a2c9186ad1ec17e5474",
    "hancoin": 1500,
    "sellEndDate": "2025/04/25 22:23",
    "listingItems": [
      "HD118B1",
      "A49CG",
      "E41Y9",
      "CT1H6"
    ]
  },
  {
    "bazaarId": "c1f4c576a17c4326beb75c7627483eab",
    "hancoin": 300,
    "sellEndDate": "2025/04/23 21:06",
    "listingItems": [
      "A49CG",
      "P127T5"
    ]
  },
  {
    "bazaarId": "ac97db8ecd7b4a69a2e89bbb8a09fc31",
    "hancoin": 6000,
    "sellEndDate": "2025/04/25 22:03",
    "listingItems": [
      "E31VB"
    ]
  },
  {
    "bazaarId": "9e9cc8034ee04343b77fcce00f130d70",
    "hancoin": 7000,
    "sellEndDate": "2025/04/25 22:02",
    "listingItems": [
      "LD213B7"
    ]
  },
  {
    "bazaarId": "2829fed8410c4bc1a07d343a6735d8c8",
    "hancoin": 12000,
    "sellEndDate": "2025/04/21 07:50",
    "listingItems": [
      "E4ZHS"
    ]
  },
  {
    "bazaarId": "548db5d2ec2f42f49a099c5f00886492",
    "hancoin": 7000,
    "sellEndDate": "2025/04/23 15:42",
    "listingItems": [
      "E4ZHS"
    ]
  },
  {
    "bazaarId": "e1ecc17ce5354bd4883ae4e940e67afd",
    "hancoin": 7000,
    "sellEndDate": "2025/04/25 22:01",
    "listingItems": [
      "E4ZHS"
    ]
  },
  {
    "bazaarId": "12553be48a994a91b1d550f155cb4b2c",
    "hancoin": 300,
    "sellEndDate": "2025/04/19 21:16",
    "listingItems": [
      "E31CR",
      "E31B2",
      "E31N7",
      "E31M"
    ]
  },
  {
    "bazaarId": "dd44ffc76ef64e4b94877bd30b0396b5",
    "hancoin": 100,
    "sellEndDate": "2025/04/21 20:54",
    "listingItems": [
      "E2114D",
      "E113TB",
      "CT110Q1",
      "A41149"
    ]
  },
  {
    "bazaarId": "0b02eadf1d3d43e9ae47bab2661d803c",
    "hancoin": 100,
    "sellEndDate": "2025/04/23 17:48",
    "listingItems": [
      "A41149",
      "A2182B",
      "A23Q9",
      "A13QL"
    ]
  },
  {
    "bazaarId": "b8c183fe13d64216842898d8be88ef5d",
    "hancoin": 500,
    "sellEndDate": "2025/04/20 19:50",
    "listingItems": [
      "E113TB",
      "AD182E"
    ]
  },
  {
    "bazaarId": "10b90b61cff6416cb2b9dac667a8f942",
    "hancoin": 100,
    "sellEndDate": "2025/04/19 17:40",
    "listingItems": [
      "AEYIK"
    ]
  },
  {
    "bazaarId": "06d13c598f934b449bfc00d8390c63bf",
    "hancoin": 100,
    "sellEndDate": "2025/04/19 17:41",
    "listingItems": [
      "AEYIK"
    ]
  },
  {
    "bazaarId": "31f9d05525614703b535bf5654897165",
    "hancoin": 100,
    "sellEndDate": "2025/04/23 23:06",
    "listingItems": [
      "AEYIK"
    ]
  },
  {
    "bazaarId": "77fa50df9ad446ceb52b35e2c521fca3",
    "hancoin": 100,
    "sellEndDate": "2025/04/21 01:53",
    "listingItems": [
      "B110R",
      "A4Y76",
      "A4BZF",
      "A4C2M"
    ]
  },
  {
    "bazaarId": "7c7310655d434c6891ed7c58bbc6b9f9",
    "hancoin": 500,
    "sellEndDate": "2025/04/21 20:18",
    "listingItems": [
      "A321148"
    ]
  },
  {
    "bazaarId": "4efdac03c1834d5f9e93ff9f53c9ab9b",
    "hancoin": 4500,
    "sellEndDate": "2025/04/21 20:17",
    "listingItems": [
      "LC2EKL"
    ]
  },
  {
    "bazaarId": "a3f95da7bd364d58b1e13736ba3cd230",
    "hancoin": 5000,
    "sellEndDate": "2025/04/19 17:59",
    "listingItems": [
      "B32CW"
    ]
  },
  {
    "bazaarId": "e090098cd1b34b84af887eaadd84c0ce",
    "hancoin": 4500,
    "sellEndDate": "2025/04/21 20:16",
    "listingItems": [
      "B32CW"
    ]
  },
  {
    "bazaarId": "c7a3e435d7654d18baad3b10700b164e",
    "hancoin": 5000,
    "sellEndDate": "2025/04/23 14:27",
    "listingItems": [
      "B32CW"
    ]
  },
  {
    "bazaarId": "79f73199221949d8a7df608931ea15a8",
    "hancoin": 2500,
    "sellEndDate": "2025/04/20 13:59",
    "listingItems": [
      "B2191"
    ]
  },
  {
    "bazaarId": "e30e5c7966654f5480a93cee8e9021c1",
    "hancoin": 2000,
    "sellEndDate": "2025/04/21 20:05",
    "listingItems": [
      "B2191"
    ]
  },
  {
    "bazaarId": "463aaae7071c492aa89f931c07d6fdd1",
    "hancoin": 1500,
    "sellEndDate": "2025/04/19 17:19",
    "listingItems": [
      "E4WLO"
    ]
  },
  {
    "bazaarId": "d846a54235c24a9d9d79c77d20ab0b8b",
    "hancoin": 2000,
    "sellEndDate": "2025/04/21 15:45",
    "listingItems": [
      "E4WLO",
      "P116F1",
      "A3123J",
      "A4BKS"
    ]
  },
  {
    "bazaarId": "72b06027c26947aea4b67f4b4128ba03",
    "hancoin": 300,
    "sellEndDate": "2025/04/25 19:37",
    "listingItems": [
      "E11MI"
    ]
  },
  {
    "bazaarId": "572561f2524d4c1b8e88d894aaa7a545",
    "hancoin": 300,
    "sellEndDate": "2025/04/25 19:37",
    "listingItems": [
      "AD182E"
    ]
  },
  {
    "bazaarId": "bbffb895e09c47fe974271dc2d03a95e",
    "hancoin": 300,
    "sellEndDate": "2025/04/25 19:35",
    "listingItems": [
      "A4ZHN"
    ]
  },
  {
    "bazaarId": "cfa30cd11ccc4035ad5fd2480fb4c9b5",
    "hancoin": 300,
    "sellEndDate": "2025/04/25 19:35",
    "listingItems": [
      "A4C6C"
    ]
  },
  {
    "bazaarId": "24fca7233bfe40b0b83022b6981d04b6",
    "hancoin": 2000,
    "sellEndDate": "2025/04/25 19:32",
    "listingItems": [
      "E420S"
    ]
  },
  {
    "bazaarId": "f0217480f5844fcf875cd56a6d90707d",
    "hancoin": 500,
    "sellEndDate": "2025/04/19 19:13",
    "listingItems": [
      "AE2JN"
    ]
  },
  {
    "bazaarId": "cd7be52d07f9425b91a9ea2b30fb2812",
    "hancoin": 300,
    "sellEndDate": "2025/04/21 19:53",
    "listingItems": [
      "HD210Q6"
    ]
  },
  {
    "bazaarId": "8a9cff3534fd4660939973cd3cf11831",
    "hancoin": 7500,
    "sellEndDate": "2025/04/20 21:40",
    "listingItems": [
      "AD10Q0",
      "ABWUM"
    ]
  },
  {
    "bazaarId": "4b72ef77ffee4c968cc681221dd87cf0",
    "hancoin": 800,
    "sellEndDate": "2025/04/21 18:26",
    "listingItems": [
      "AA12IY"
    ]
  },
  {
    "bazaarId": "9d820bbf4f654067be6504202e405826",
    "hancoin": 800,
    "sellEndDate": "2025/04/21 18:26",
    "listingItems": [
      "AA12IY"
    ]
  },
  {
    "bazaarId": "b959b58d0bbc4c52bb95f74131fffc0f",
    "hancoin": 500,
    "sellEndDate": "2025/04/19 14:02",
    "listingItems": [
      "HD2198X"
    ]
  },
  {
    "bazaarId": "57432b323e964ffea097dba69f2afc7e",
    "hancoin": 1700,
    "sellEndDate": "2025/04/20 20:14",
    "listingItems": [
      "HD218FJ",
      "HD2198X",
      "HD2182I"
    ]
  },
  {
    "bazaarId": "6134e0828dec403397e46fbb61b3aef5",
    "hancoin": 800,
    "sellEndDate": "2025/04/25 18:17",
    "listingItems": [
      "E4YIM"
    ]
  },
  {
    "bazaarId": "7285f2ccbfb840c5b973eaf4324d8cce",
    "hancoin": 1500,
    "sellEndDate": "2025/04/20 02:57",
    "listingItems": [
      "P115J1",
      "A247O",
      "E21KU",
      "E1XXH"
    ]
  },
  {
    "bazaarId": "2165276b600247718abb5d93b4bdc66d",
    "hancoin": 500,
    "sellEndDate": "2025/04/24 19:09",
    "listingItems": [
      "E1XXH"
    ]
  },
  {
    "bazaarId": "d0de89dc5a1144a3b9c55212471589c2",
    "hancoin": 500,
    "sellEndDate": "2025/04/24 19:14",
    "listingItems": [
      "E1XXH"
    ]
  },
  {
    "bazaarId": "a76d9a7702c34d0d8b36a4348a9ca6f4",
    "hancoin": 400,
    "sellEndDate": "2025/04/25 16:36",
    "listingItems": [
      "E1XXH"
    ]
  },
  {
    "bazaarId": "37793f9ee2114fa29538cf252acc413e",
    "hancoin": 700,
    "sellEndDate": "2025/04/22 08:41",
    "listingItems": [
      "B111LL"
    ]
  },
  {
    "bazaarId": "10a58973479445c781b042beb13cc41f",
    "hancoin": 400,
    "sellEndDate": "2025/04/25 16:36",
    "listingItems": [
      "B111LL"
    ]
  },
  {
    "bazaarId": "8e17fdb51a834089aeed39ebd30a9533",
    "hancoin": 500,
    "sellEndDate": "2025/04/24 21:34",
    "listingItems": [
      "E22AR"
    ]
  },
  {
    "bazaarId": "734f1beb57fe4eef98893a25f1af9a83",
    "hancoin": 500,
    "sellEndDate": "2025/04/20 20:31",
    "listingItems": [
      "A4BKS"
    ]
  },
  {
    "bazaarId": "cb0ba5adf5d344da80f52d518a23baba",
    "hancoin": 100,
    "sellEndDate": "2025/04/23 16:44",
    "listingItems": [
      "LC1ED7",
      "A49KX",
      "E11JP",
      "A4C86"
    ]
  },
  {
    "bazaarId": "30ede75cb0e14f899869ed41e5ea83c5",
    "hancoin": 5000,
    "sellEndDate": "2025/04/23 18:38",
    "listingItems": [
      "E41UA"
    ]
  },
  {
    "bazaarId": "82e90a7144ba4ed488cb5f91cacc0259",
    "hancoin": 500,
    "sellEndDate": "2025/04/19 14:00",
    "listingItems": [
      "AE25M"
    ]
  },
  {
    "bazaarId": "e6520ebbb20047ddbc7f33749b137cf3",
    "hancoin": 3500,
    "sellEndDate": "2025/04/19 16:40",
    "listingItems": [
      "ADUAE"
    ]
  },
  {
    "bazaarId": "e1a5c087d80b40cea4bdb11cbbb2d2b5",
    "hancoin": 3000,
    "sellEndDate": "2025/04/19 14:48",
    "listingItems": [
      "AFUQ",
      "A24EB",
      "AB2RR",
      "E31HS"
    ]
  },
  {
    "bazaarId": "de297bf5728b4bfc8f670d9d476e860d",
    "hancoin": 2000,
    "sellEndDate": "2025/04/23 14:11",
    "listingItems": [
      "E31HS"
    ]
  },
  {
    "bazaarId": "b4782dfd4b58434cab35ad816792e6aa",
    "hancoin": 2000,
    "sellEndDate": "2025/04/23 14:11",
    "listingItems": [
      "E31HS"
    ]
  },
  {
    "bazaarId": "fae28b6c48ab4a9ea4f7f7288aa85e84",
    "hancoin": 2000,
    "sellEndDate": "2025/04/23 14:57",
    "listingItems": [
      "AB2RR"
    ]
  },
  {
    "bazaarId": "7bbb1a806a8548158be51da427ea04a6",
    "hancoin": 1800,
    "sellEndDate": "2025/04/19 19:51",
    "listingItems": [
      "A24EB"
    ]
  },
  {
    "bazaarId": "5510251b18a74c81b9f173ed8c0c8456",
    "hancoin": 300,
    "sellEndDate": "2025/04/21 14:45",
    "listingItems": [
      "A45DZ",
      "P11865",
      "LD118XN"
    ]
  },
  {
    "bazaarId": "d8c6733291284200b3518a194b2df542",
    "hancoin": 100,
    "sellEndDate": "2025/04/21 14:44",
    "listingItems": [
      "A12RV",
      "LC1B5U",
      "P1176C",
      "B1N5"
    ]
  },
  {
    "bazaarId": "0f4f70744b0b4c40a1b28c067dec0e99",
    "hancoin": 200,
    "sellEndDate": "2025/04/21 14:41",
    "listingItems": [
      "E41NP",
      "B31C6"
    ]
  },
  {
    "bazaarId": "04ad316bfbac47d0b20682864d70a047",
    "hancoin": 200,
    "sellEndDate": "2025/04/21 14:40",
    "listingItems": [
      "AB2HF"
    ]
  },
  {
    "bazaarId": "9dcfb56e1b2847a3b36e94a02b1e3865",
    "hancoin": 100,
    "sellEndDate": "2025/04/20 22:11",
    "listingItems": [
      "LD249Y",
      "B32A0",
      "AFX4",
      "E41N0"
    ]
  },
  {
    "bazaarId": "1486ac233f444b12b18941dad9fa8307",
    "hancoin": 100,
    "sellEndDate": "2025/04/22 05:44",
    "listingItems": [
      "LD249Y",
      "A4A2F"
    ]
  },
  {
    "bazaarId": "db58663a40e841e489db129a4e836163",
    "hancoin": 100,
    "sellEndDate": "2025/04/24 22:34",
    "listingItems": [
      "LD259T",
      "LD249Y",
      "P1266L",
      "P12675"
    ]
  },
  {
    "bazaarId": "429438e84f2b4781bd2cf412c48c8f43",
    "hancoin": 100,
    "sellEndDate": "2025/04/25 13:49",
    "listingItems": [
      "LD249Y",
      "P127OB"
    ]
  },
  {
    "bazaarId": "14f9aefea3d14982bd1fdf8bbadb72fe",
    "hancoin": 100,
    "sellEndDate": "2025/04/25 14:12",
    "listingItems": [
      "LD249Y",
      "P127OB"
    ]
  },
  {
    "bazaarId": "5159b33b5b7447d4884c21de15bc5da8",
    "hancoin": 300,
    "sellEndDate": "2025/04/19 13:22",
    "listingItems": [
      "P127T5"
    ]
  },
  {
    "bazaarId": "6110c6cb56e74e8090c18e379cd42e3b",
    "hancoin": 400,
    "sellEndDate": "2025/04/19 13:22",
    "listingItems": [
      "A15HS"
    ]
  },
  {
    "bazaarId": "cb7a717f65284462a992481e508f59f6",
    "hancoin": 4300,
    "sellEndDate": "2025/04/23 11:16",
    "listingItems": [
      "E221J"
    ]
  },
  {
    "bazaarId": "c5a57eb55d89439ab1d7969e94a1d713",
    "hancoin": 3500,
    "sellEndDate": "2025/04/19 14:00",
    "listingItems": [
      "AB3QV"
    ]
  },
  {
    "bazaarId": "f538ad6301504aa1a3bbbad71649f50d",
    "hancoin": 100,
    "sellEndDate": "2025/04/20 11:18",
    "listingItems": [
      "E41O5"
    ]
  },
  {
    "bazaarId": "d32851bf4ce84bebb7f60935b79cb68a",
    "hancoin": 1200,
    "sellEndDate": "2025/04/19 20:14",
    "listingItems": [
      "A495Y",
      "B1ER",
      "P128LL",
      "HD218FJ"
    ]
  },
  {
    "bazaarId": "376e0b6e9c6a449c8cf44b3fd9e229b5",
    "hancoin": 500,
    "sellEndDate": "2025/04/20 02:56",
    "listingItems": [
      "A495Y",
      "LC1EJR",
      "AB1OB",
      "P114HO"
    ]
  },
  {
    "bazaarId": "4b700d53709f4cd78e56e77d1e136933",
    "hancoin": 600,
    "sellEndDate": "2025/04/20 02:56",
    "listingItems": [
      "A495Y",
      "E21E9",
      "P1153S",
      "E1111"
    ]
  },
  {
    "bazaarId": "ea5d662387ed4a1cbe28ae34afa667a3",
    "hancoin": 500,
    "sellEndDate": "2025/04/22 21:12",
    "listingItems": [
      "AA3G9",
      "P112WY",
      "A12KY",
      "A495Y"
    ]
  },
  {
    "bazaarId": "3db47769464945d5a03be2bf30d0d4e5",
    "hancoin": 100,
    "sellEndDate": "2025/04/25 10:37",
    "listingItems": [
      "P11347",
      "LC1ECZ",
      "E1TN",
      "AF1IC"
    ]
  },
  {
    "bazaarId": "5410692ff9eb436591b4912ff45372ba",
    "hancoin": 2000,
    "sellEndDate": "2025/04/23 01:07",
    "listingItems": [
      "A3113KU",
      "A2XKS",
      "AF150",
      "E31ZC"
    ]
  },
  {
    "bazaarId": "0f3305d821084a0487321f07959b0dac",
    "hancoin": 800,
    "sellEndDate": "2025/04/23 14:05",
    "listingItems": [
      "A2XKS"
    ]
  },
  {
    "bazaarId": "172368299129490c9eb893dd56428a47",
    "hancoin": 2000,
    "sellEndDate": "2025/04/23 16:49",
    "listingItems": [
      "A2XKS",
      "A411WW",
      "P1212ZG",
      "A3213KV"
    ]
  },
  {
    "bazaarId": "2e65340cfe8c43eeb46cbe0004cd14ca",
    "hancoin": 100,
    "sellEndDate": "2025/04/25 10:37",
    "listingItems": [
      "P114XT",
      "LC1EB8",
      "E4UV",
      "A4A6K"
    ]
  },
  {
    "bazaarId": "0c047f29dbf34b9a8ddd7dd6ba3e97c6",
    "hancoin": 300,
    "sellEndDate": "2025/04/19 16:18",
    "listingItems": [
      "E4UV",
      "P115S0",
      "E4WN",
      "P1118D"
    ]
  },
  {
    "bazaarId": "a659a2455c354ff8b8c408e7edc1c9cb",
    "hancoin": 100,
    "sellEndDate": "2025/04/21 08:34",
    "listingItems": [
      "ADAK",
      "AA1ME",
      "ABDU",
      "E21A2"
    ]
  },
  {
    "bazaarId": "6c3f2cf1b7ee4e4b9555e246a0ea3ca0",
    "hancoin": 200,
    "sellEndDate": "2025/04/23 01:10",
    "listingItems": [
      "AAUR",
      "ABDU",
      "P111HX",
      "LC1A73"
    ]
  },
  {
    "bazaarId": "d74e0291495b49b28af0a990c57c1a4c",
    "hancoin": 100,
    "sellEndDate": "2025/04/24 22:36",
    "listingItems": [
      "E21WJ",
      "A4AU3",
      "E41N0",
      "B32A0"
    ]
  },
  {
    "bazaarId": "19687c43e9744edda166f4f6c347afd2",
    "hancoin": 300,
    "sellEndDate": "2025/04/25 07:53",
    "listingItems": [
      "A2182B",
      "A118AW",
      "B233L",
      "P1118SN"
    ]
  },
  {
    "bazaarId": "574e47fda85a44d98eb5edb4b6ad6548",
    "hancoin": 300,
    "sellEndDate": "2025/04/20 02:55",
    "listingItems": [
      "LD1105H",
      "A118AW",
      "A3114L",
      "P114HO"
    ]
  },
  {
    "bazaarId": "dc52ea0a568d4d9aad137d1a8223c651",
    "hancoin": 100,
    "sellEndDate": "2025/04/20 13:22",
    "listingItems": [
      "E112ZA",
      "A118AW",
      "P1118SN",
      "LD1198Y"
    ]
  },
  {
    "bazaarId": "a26a2fefb59746b5a821d99d60234705",
    "hancoin": 300,
    "sellEndDate": "2025/04/20 20:08",
    "listingItems": [
      "B1YP"
    ]
  },
  {
    "bazaarId": "74c0bdca157a43eab7591c07ac50a25b",
    "hancoin": 4500,
    "sellEndDate": "2025/04/24 20:51",
    "listingItems": [
      "E11JU"
    ]
  },
  {
    "bazaarId": "c9e1b6abb52b49a6aaf8443abe7c2657",
    "hancoin": 100,
    "sellEndDate": "2025/04/25 03:54",
    "listingItems": [
      "A31152",
      "A23UN",
      "E414T",
      "P1132J"
    ]
  },
  {
    "bazaarId": "e9c859089dae49ad84e3b0f72ee920e4",
    "hancoin": 100,
    "sellEndDate": "2025/04/25 03:53",
    "listingItems": [
      "E1QV",
      "LC1AXI",
      "P113AW",
      "A31122"
    ]
  },
  {
    "bazaarId": "e387c3158b534a3bbbb5238067940c13",
    "hancoin": 100,
    "sellEndDate": "2025/04/19 23:19",
    "listingItems": [
      "A247O"
    ]
  },
  {
    "bazaarId": "30921b54ae1f4f9a9d22c21e9be08bae",
    "hancoin": 100,
    "sellEndDate": "2025/04/19 13:50",
    "listingItems": [
      "CT210Q2",
      "AA10PZ",
      "E411X0",
      "ADX9L"
    ]
  },
  {
    "bazaarId": "1502ddd3382448918fc10648ed7b9a51",
    "hancoin": 100,
    "sellEndDate": "2025/04/23 23:40",
    "listingItems": [
      "ADTRX",
      "P1118XP",
      "LD118FK",
      "HD118XL"
    ]
  },
  {
    "bazaarId": "8a5f912f75e74043a06df61ced2811a2",
    "hancoin": 200,
    "sellEndDate": "2025/04/24 17:52",
    "listingItems": [
      "LD213TF"
    ]
  },
  {
    "bazaarId": "306691a42b9543aeb1ff090e951adca4",
    "hancoin": 1000,
    "sellEndDate": "2025/04/24 13:46",
    "listingItems": [
      "FA2117"
    ]
  },
  {
    "bazaarId": "1e81cd68e4744b7585662ea7d75d000a",
    "hancoin": 800,
    "sellEndDate": "2025/04/25 00:39",
    "listingItems": [
      "FA2117"
    ]
  },
  {
    "bazaarId": "f21f663ef95b41428e0868ae35559377",
    "hancoin": 3500,
    "sellEndDate": "2025/04/21 00:32",
    "listingItems": [
      "AF14G"
    ]
  },
  {
    "bazaarId": "e8814e81901b4021994eb755965dff42",
    "hancoin": 4000,
    "sellEndDate": "2025/04/24 22:48",
    "listingItems": [
      "AF14G"
    ]
  },
  {
    "bazaarId": "5bbf7536dad243a7a53b55f5d5d713fc",
    "hancoin": 200,
    "sellEndDate": "2025/04/19 14:01",
    "listingItems": [
      "B1GE"
    ]
  },
  {
    "bazaarId": "bebdeab515e24197bcfd515ead7b90a6",
    "hancoin": 100,
    "sellEndDate": "2025/04/23 12:03",
    "listingItems": [
      "ABX9"
    ]
  },
  {
    "bazaarId": "debea92f724f4c1b9ada6470afe10fea",
    "hancoin": 600,
    "sellEndDate": "2025/04/24 23:35",
    "listingItems": [
      "AB47Y",
      "AE4XF",
      "CT2TY"
    ]
  },
  {
    "bazaarId": "79a636573eae49f79410273444c4821b",
    "hancoin": 200,
    "sellEndDate": "2025/04/19 14:02",
    "listingItems": [
      "AA2PA"
    ]
  },
  {
    "bazaarId": "c506dd3e8215442f8d3437e1819063eb",
    "hancoin": 200,
    "sellEndDate": "2025/04/19 19:29",
    "listingItems": [
      "AA2PA",
      "A41059",
      "LD2182K",
      "HD218B2"
    ]
  },
  {
    "bazaarId": "3b5b784e37944bce864c989fbf2e2d65",
    "hancoin": 200,
    "sellEndDate": "2025/04/24 22:58",
    "listingItems": [
      "LC1AXJ",
      "A31211",
      "AA2PA",
      "P118C2"
    ]
  },
  {
    "bazaarId": "8a1b41adc9e04ade83b1423e5e27a838",
    "hancoin": 300,
    "sellEndDate": "2025/04/24 22:42",
    "listingItems": [
      "E4O2",
      "AB45K",
      "P118C2",
      "A4B6B"
    ]
  },
  {
    "bazaarId": "fe0d07560fc1495d97bb393b8d756b1f",
    "hancoin": 500,
    "sellEndDate": "2025/04/24 21:22",
    "listingItems": [
      "AE3U8"
    ]
  },
  {
    "bazaarId": "91c5bb3f24254e5dafbe80361fcf8699",
    "hancoin": 800,
    "sellEndDate": "2025/04/19 23:03",
    "listingItems": [
      "AFSB"
    ]
  },
  {
    "bazaarId": "4e68e3f90272416cb065999c158d3de8",
    "hancoin": 1500,
    "sellEndDate": "2025/04/22 14:26",
    "listingItems": [
      "AFSB"
    ]
  },
  {
    "bazaarId": "96eb90b19fea4d04919df76869ce4843",
    "hancoin": 1000,
    "sellEndDate": "2025/04/24 22:50",
    "listingItems": [
      "LC1DEZ",
      "E3201",
      "P1166B",
      "AFSB"
    ]
  },
  {
    "bazaarId": "a13b17759169449f8cb995ddad664abe",
    "hancoin": 200,
    "sellEndDate": "2025/04/19 22:43",
    "listingItems": [
      "A4D3B",
      "P1153S",
      "P111M3",
      "E3201"
    ]
  },
  {
    "bazaarId": "ce317dfa44f84890b7d596489a36e9b0",
    "hancoin": 500,
    "sellEndDate": "2025/04/21 23:54",
    "listingItems": [
      "P126K9",
      "E3201",
      "CT2UT",
      "E41M6"
    ]
  },
  {
    "bazaarId": "0f269b7da37e48fab543befc066c719c",
    "hancoin": 5000,
    "sellEndDate": "2025/04/24 22:47",
    "listingItems": [
      "B1176"
    ]
  },
  {
    "bazaarId": "6b0beb5cd3b347f0a6208e2665c75646",
    "hancoin": 100,
    "sellEndDate": "2025/04/24 22:36",
    "listingItems": [
      "ADP9",
      "AFX4"
    ]
  },
  {
    "bazaarId": "59751d172e3a4a08b4503ea3f76ceefe",
    "hancoin": 400,
    "sellEndDate": "2025/04/23 17:56",
    "listingItems": [
      "A1ZW4"
    ]
  },
  {
    "bazaarId": "18839bd5f84f46ccbaf4f02de4cafe36",
    "hancoin": 100,
    "sellEndDate": "2025/04/20 21:04",
    "listingItems": [
      "P1218SO"
    ]
  },
  {
    "bazaarId": "ab075e4d551745c4aae80cc3fc80126e",
    "hancoin": 200,
    "sellEndDate": "2025/04/24 19:25",
    "listingItems": [
      "P1218SO",
      "LC2D6V"
    ]
  },
  {
    "bazaarId": "5829898ea33443759e76cad8c0c38e06",
    "hancoin": 1800,
    "sellEndDate": "2025/04/24 19:59",
    "listingItems": [
      "LC2EH7",
      "CT2U0",
      "P1218SO",
      "HD218FJ"
    ]
  },
  {
    "bazaarId": "e7ed9448f3e54f809949d43fd2a5ba84",
    "hancoin": 100,
    "sellEndDate": "2025/04/20 16:18",
    "listingItems": [
      "LC2E4N"
    ]
  },
  {
    "bazaarId": "9391c8ae00e04a3c8264b67c6687fbd3",
    "hancoin": 2000,
    "sellEndDate": "2025/04/20 22:59",
    "listingItems": [
      "E31J2"
    ]
  },
  {
    "bazaarId": "de35c057edb4417aa7dfa26ace7e5ecf",
    "hancoin": 6000,
    "sellEndDate": "2025/04/23 19:26",
    "listingItems": [
      "A26I2"
    ]
  },
  {
    "bazaarId": "1fd48ca3ae7341f3916bdec8590f4e69",
    "hancoin": 100,
    "sellEndDate": "2025/04/23 14:05",
    "listingItems": [
      "AA114A",
      "LD118SL"
    ]
  },
  {
    "bazaarId": "e019ebe440674d66ac880fc5013814da",
    "hancoin": 1400,
    "sellEndDate": "2025/04/24 19:47",
    "listingItems": [
      "LD118XN",
      "P1118XP",
      "AE2ZH",
      "A14BP"
    ]
  },
  {
    "bazaarId": "9171168cddb2434b9b8dbe1b7cc1a5b8",
    "hancoin": 600,
    "sellEndDate": "2025/04/22 01:07",
    "listingItems": [
      "A411WW"
    ]
  },
  {
    "bazaarId": "a8095eb05e5140dcb7991f233649b9b3",
    "hancoin": 700,
    "sellEndDate": "2025/04/22 08:42",
    "listingItems": [
      "A411WW"
    ]
  },
  {
    "bazaarId": "0040ce142bae4a16837236fcdf97d0ff",
    "hancoin": 300,
    "sellEndDate": "2025/04/24 21:35",
    "listingItems": [
      "A411WW"
    ]
  },
  {
    "bazaarId": "9b1c85c6d110478f8004a7c968ef7a33",
    "hancoin": 1000,
    "sellEndDate": "2025/04/24 21:18",
    "listingItems": [
      "AAZHO",
      "A312GH",
      "B31B4"
    ]
  },
  {
    "bazaarId": "40bdd441e6374e2a86b5da69aae747bb",
    "hancoin": 200,
    "sellEndDate": "2025/04/20 21:17",
    "listingItems": [
      "B229L"
    ]
  },
  {
    "bazaarId": "26b5dfbf565d41e3b36a802c3d5df6c5",
    "hancoin": 100,
    "sellEndDate": "2025/04/20 21:17",
    "listingItems": [
      "AF1BC"
    ]
  },
  {
    "bazaarId": "3eab9a294a6c4a00917dcd0a7af4e265",
    "hancoin": 100,
    "sellEndDate": "2025/04/20 21:16",
    "listingItems": [
      "A462E",
      "A23QY",
      "A13EW"
    ]
  },
  {
    "bazaarId": "7935f34135f344b9a7b40ffccdcf18bc",
    "hancoin": 1900,
    "sellEndDate": "2025/04/19 19:26",
    "listingItems": [
      "LD211GI",
      "E2X9P",
      "A2Y75",
      "A3213KV"
    ]
  },
  {
    "bazaarId": "2227181f73ef45e7bb1ab3e263850f63",
    "hancoin": 1000,
    "sellEndDate": "2025/04/20 21:13",
    "listingItems": [
      "LD211GI"
    ]
  },
  {
    "bazaarId": "41c939cb302b43c2bcdb7745adae11fe",
    "hancoin": 1500,
    "sellEndDate": "2025/04/20 21:08",
    "listingItems": [
      "P12YO5"
    ]
  },
  {
    "bazaarId": "4c0471d4b8e745afae198b61d1af386c",
    "hancoin": 300,
    "sellEndDate": "2025/04/20 21:02",
    "listingItems": [
      "P12WLS"
    ]
  },
  {
    "bazaarId": "53560e23788a40a2b75aae4eefdac762",
    "hancoin": 1600,
    "sellEndDate": "2025/04/24 20:44",
    "listingItems": [
      "A411GC",
      "LD1114E",
      "AD10AQ",
      "E2Y7A"
    ]
  },
  {
    "bazaarId": "0dc3ff8c240d43fc8fa211141133a7c4",
    "hancoin": 300,
    "sellEndDate": "2025/04/20 20:44",
    "listingItems": [
      "AFWUN"
    ]
  },
  {
    "bazaarId": "28bbad57eb3a4225aaed7514aa916b00",
    "hancoin": 800,
    "sellEndDate": "2025/04/23 21:34",
    "listingItems": [
      "A23ZG",
      "E1RU",
      "AFWUN",
      "E21AZ"
    ]
  },
  {
    "bazaarId": "7a355c2356f849c4a8fa608bd815dfff",
    "hancoin": 300,
    "sellEndDate": "2025/04/20 20:35",
    "listingItems": [
      "AE4RM"
    ]
  },
  {
    "bazaarId": "0d4ddb9c44ca4aa4bb47a6e30f49379c",
    "hancoin": 300,
    "sellEndDate": "2025/04/23 10:49",
    "listingItems": [
      "AE4RM"
    ]
  },
  {
    "bazaarId": "fe6bfcd41a374e10b4720bc2e3c1ab59",
    "hancoin": 300,
    "sellEndDate": "2025/04/20 20:34",
    "listingItems": [
      "CT2DY"
    ]
  },
  {
    "bazaarId": "7fec4d74adee43229eb4b62e2c1d38ba",
    "hancoin": 300,
    "sellEndDate": "2025/04/20 20:26",
    "listingItems": [
      "LC2EMP"
    ]
  },
  {
    "bazaarId": "d021e935c6984c4896d5fcb9bcdb66fb",
    "hancoin": 800,
    "sellEndDate": "2025/04/20 20:26",
    "listingItems": [
      "LD218XO"
    ]
  },
  {
    "bazaarId": "a35b87248ea14d558d8abdb69017957c",
    "hancoin": 700,
    "sellEndDate": "2025/04/20 20:20",
    "listingItems": [
      "LC2EN1"
    ]
  },
  {
    "bazaarId": "184b451de045450caaf079c4bd8f6e19",
    "hancoin": 300,
    "sellEndDate": "2025/04/23 15:57",
    "listingItems": [
      "AB3NX"
    ]
  },
  {
    "bazaarId": "62f92e51220b424c920fa1aac8b571a1",
    "hancoin": 900,
    "sellEndDate": "2025/04/20 20:15",
    "listingItems": [
      "HD218SK"
    ]
  },
  {
    "bazaarId": "b78c2335ba8f426fa0293ebd763d2315",
    "hancoin": 700,
    "sellEndDate": "2025/04/24 18:15",
    "listingItems": [
      "HD2182I"
    ]
  },
  {
    "bazaarId": "dc651e25481945f485259891deae041a",
    "hancoin": 400,
    "sellEndDate": "2025/04/23 10:37",
    "listingItems": [
      "E11E1",
      "HD218FJ"
    ]
  },
  {
    "bazaarId": "ce5cdce7d7d54b5f9825e11dd0be178b",
    "hancoin": 1800,
    "sellEndDate": "2025/04/24 20:01",
    "listingItems": [
      "A3213KV",
      "E41UW",
      "A1598",
      "B2MY"
    ]
  },
  {
    "bazaarId": "194d1189538842169a8da6ccad911770",
    "hancoin": 300,
    "sellEndDate": "2025/04/24 17:51",
    "listingItems": [
      "A3213KV"
    ]
  },
  {
    "bazaarId": "62f805e7bc424894a7670035f65b70c9",
    "hancoin": 3000,
    "sellEndDate": "2025/04/19 21:14",
    "listingItems": [
      "B2MY"
    ]
  },
  {
    "bazaarId": "bcd32d1f8b2c41a38a4cae5a14a972a9",
    "hancoin": 1100,
    "sellEndDate": "2025/04/23 15:00",
    "listingItems": [
      "B2MY"
    ]
  },
  {
    "bazaarId": "d761f5d7d733428599e07cbbf10f9890",
    "hancoin": 300,
    "sellEndDate": "2025/04/20 20:00",
    "listingItems": [
      "A412IX"
    ]
  },
  {
    "bazaarId": "a69cdd99e13044c7af19462b7ad06732",
    "hancoin": 1000,
    "sellEndDate": "2025/04/19 20:14",
    "listingItems": [
      "P125L0"
    ]
  },
  {
    "bazaarId": "87af4107be51434d967a7ba21bb9001b",
    "hancoin": 100,
    "sellEndDate": "2025/04/21 04:58",
    "listingItems": [
      "A215F",
      "A481L",
      "A23XB",
      "P11465"
    ]
  },
  {
    "bazaarId": "18baca8524ee4ddf90461b9984fcc5aa",
    "hancoin": 100,
    "sellEndDate": "2025/04/24 19:27",
    "listingItems": [
      "A23XB"
    ]
  },
  {
    "bazaarId": "0be68091a708409dbe7742826c31f31e",
    "hancoin": 200,
    "sellEndDate": "2025/04/23 15:24",
    "listingItems": [
      "A4CRZ",
      "E41M6",
      "AE19N",
      "AE13K"
    ]
  },
  {
    "bazaarId": "96db6fa084bb4c22a122e5d67d3ded44",
    "hancoin": 100,
    "sellEndDate": "2025/04/24 19:27",
    "listingItems": [
      "E41M6"
    ]
  },
  {
    "bazaarId": "f5124fdee2824a94b19a087bb259a6ce",
    "hancoin": 400,
    "sellEndDate": "2025/04/24 19:20",
    "listingItems": [
      "P126H0"
    ]
  },
  {
    "bazaarId": "0d6c743dab174ee3af438364ea867288",
    "hancoin": 100,
    "sellEndDate": "2025/04/24 18:56",
    "listingItems": [
      "E4XT",
      "P1118XP",
      "CT1TO",
      "LD118SL"
    ]
  },
  {
    "bazaarId": "3f00449a91314ec98dcb34b52cf4ae55",
    "hancoin": 2000,
    "sellEndDate": "2025/04/24 17:44",
    "listingItems": [
      "LC2EGD"
    ]
  },
  {
    "bazaarId": "d412ad2a6f294566bd0bf64a24dcf69d",
    "hancoin": 100,
    "sellEndDate": "2025/04/20 01:05",
    "listingItems": [
      "AA2WB",
      "A4CRZ",
      "P1118SN",
      "P1188O"
    ]
  },
  {
    "bazaarId": "19737f303d4744b5b294951d857b2699",
    "hancoin": 200,
    "sellEndDate": "2025/04/22 21:16",
    "listingItems": [
      "E4R3",
      "AE19N",
      "AA2WB",
      "P1118SN"
    ]
  },
  {
    "bazaarId": "d45d962b79b74f2dbfbbef04ff2ffda2",
    "hancoin": 100,
    "sellEndDate": "2025/04/21 16:21",
    "listingItems": [
      "P121W4"
    ]
  },
  {
    "bazaarId": "d27fd3ffc6ed4beaa491e3d441d63b62",
    "hancoin": 100,
    "sellEndDate": "2025/04/24 16:11",
    "listingItems": [
      "P121W4",
      "P121ZN",
      "HD216",
      "HD20V"
    ]
  },
  {
    "bazaarId": "0f476392404b421688d930eee5b4a8c6",
    "hancoin": 100,
    "sellEndDate": "2025/04/21 01:44",
    "listingItems": [
      "A44NE",
      "A12OL",
      "A45HH",
      "A215F"
    ]
  },
  {
    "bazaarId": "3d8e7f71c20344b580e299ed17b7d909",
    "hancoin": 100,
    "sellEndDate": "2025/04/20 13:22",
    "listingItems": [
      "AF1FE",
      "E11HY",
      "AA3JB",
      "CT1R4"
    ]
  },
  {
    "bazaarId": "9a451a3893db4f8b9008956b4370bdcc",
    "hancoin": 600,
    "sellEndDate": "2025/04/24 11:55",
    "listingItems": [
      "P128LL"
    ]
  },
  {
    "bazaarId": "5087d4665e4942c38fdac69e398b6982",
    "hancoin": 4000,
    "sellEndDate": "2025/04/20 10:53",
    "listingItems": [
      "B2209"
    ]
  },
  {
    "bazaarId": "cf79b2e72dc047b7bacc4549e9c18bbf",
    "hancoin": 200,
    "sellEndDate": "2025/04/20 10:26",
    "listingItems": [
      "A1Z8K",
      "AA1YE",
      "E22AX",
      "LD110Q7"
    ]
  },
  {
    "bazaarId": "77fd9820e8e84f0da7e4be0fad057de8",
    "hancoin": 4800,
    "sellEndDate": "2025/04/21 20:54",
    "listingItems": [
      "A14TM"
    ]
  },
  {
    "bazaarId": "4d91ceb615c84a01b5a12ec42ee0d690",
    "hancoin": 4500,
    "sellEndDate": "2025/04/24 10:18",
    "listingItems": [
      "A14TM"
    ]
  },
  {
    "bazaarId": "d35043d8b08c44b49b56996957dfea84",
    "hancoin": 200,
    "sellEndDate": "2025/04/22 20:48",
    "listingItems": [
      "LD118SL",
      "AFMQ",
      "E31F9",
      "P11SN"
    ]
  },
  {
    "bazaarId": "5b6222b57f8e4564af9d1d60d4978f92",
    "hancoin": 200,
    "sellEndDate": "2025/04/20 09:53",
    "listingItems": [
      "AE2V0",
      "A4CLK",
      "P1155J",
      "LC1EDV"
    ]
  },
  {
    "bazaarId": "eaf940aed0c44cca8973af3081acbc1e",
    "hancoin": 800,
    "sellEndDate": "2025/04/23 14:05",
    "listingItems": [
      "A3211GB"
    ]
  },
  {
    "bazaarId": "49349cbbfedd473e892e4b1fd4499821",
    "hancoin": 100,
    "sellEndDate": "2025/04/19 17:40",
    "listingItems": [
      "B112EI"
    ]
  },
  {
    "bazaarId": "249724b0517043b794bea35432f0726e",
    "hancoin": 100,
    "sellEndDate": "2025/04/20 09:02",
    "listingItems": [
      "AAUR",
      "AAWZ",
      "A239V",
      "A12TA"
    ]
  },
  {
    "bazaarId": "391b130d4ec3478cadb96c3f56e209ef",
    "hancoin": 100,
    "sellEndDate": "2025/04/20 02:59",
    "listingItems": [
      "AA108",
      "A3113E",
      "A12TA",
      "A215F"
    ]
  },
  {
    "bazaarId": "2d37ad7ec5f1480bba88679bd57b099c",
    "hancoin": 100,
    "sellEndDate": "2025/04/21 01:45",
    "listingItems": [
      "P11ZW",
      "A467F",
      "A239V"
    ]
  },
  {
    "bazaarId": "129313da237243b4b66ece8cefedaa09",
    "hancoin": 100,
    "sellEndDate": "2025/04/21 18:38",
    "listingItems": [
      "A45A2",
      "AAUR",
      "LC1CS6",
      "P111HX"
    ]
  },
  {
    "bazaarId": "824f7863aa1c4056bea079d3e7f34279",
    "hancoin": 5000,
    "sellEndDate": "2025/04/20 07:54",
    "listingItems": [
      "A26HJ"
    ]
  },
  {
    "bazaarId": "c7bbdf4bdca74039a0fb4354466b9654",
    "hancoin": 6000,
    "sellEndDate": "2025/04/24 01:41",
    "listingItems": [
      "A26HJ"
    ]
  },
  {
    "bazaarId": "0808ed9bf79d4a9397c12280bcf9048f",
    "hancoin": 6500,
    "sellEndDate": "2025/04/20 02:59",
    "listingItems": [
      "A4TRV"
    ]
  },
  {
    "bazaarId": "2f225c2dad2242ea970f82107d34d32e",
    "hancoin": 200,
    "sellEndDate": "2025/04/20 05:54",
    "listingItems": [
      "A2Y75"
    ]
  },
  {
    "bazaarId": "c09b9e638d76467ab8e21284796b4897",
    "hancoin": 700,
    "sellEndDate": "2025/04/22 08:40",
    "listingItems": [
      "A2Y75"
    ]
  },
  {
    "bazaarId": "f0866bfb224b43bc9ac4f3ee146c47d5",
    "hancoin": 200,
    "sellEndDate": "2025/04/20 03:00",
    "listingItems": [
      "E41ET",
      "P1118SN",
      "LC1ECG",
      "AA23S"
    ]
  },
  {
    "bazaarId": "f116be7a6a3b43f3ba4b93cfd2807f44",
    "hancoin": 100,
    "sellEndDate": "2025/04/22 16:31",
    "listingItems": [
      "AA3RE",
      "A215F",
      "P113DD"
    ]
  },
  {
    "bazaarId": "02c74639190a4b4a992dcc4c001b8e06",
    "hancoin": 300,
    "sellEndDate": "2025/04/19 19:16",
    "listingItems": [
      "E21KU"
    ]
  },
  {
    "bazaarId": "f7a5ab82b9a74033a212dc9e4a419bc3",
    "hancoin": 100,
    "sellEndDate": "2025/04/19 23:18",
    "listingItems": [
      "E21KU"
    ]
  },
  {
    "bazaarId": "f1c29f3fcb2c4cdfbbca05338c150978",
    "hancoin": 600,
    "sellEndDate": "2025/04/22 05:51",
    "listingItems": [
      "E21KU",
      "B2CC",
      "B31BA",
      "A3124A"
    ]
  },
  {
    "bazaarId": "85c32e92013b44e08d74b8893e405c2f",
    "hancoin": 600,
    "sellEndDate": "2025/04/23 15:30",
    "listingItems": [
      "E21KU"
    ]
  },
  {
    "bazaarId": "5ce31e62e6c64ff3a5e3b55ce31101f2",
    "hancoin": 400,
    "sellEndDate": "2025/04/20 02:57",
    "listingItems": [
      "AE2IR",
      "A24G3",
      "CT1FQ",
      "AA224"
    ]
  },
  {
    "bazaarId": "ea3734fe6708429ca88dfc6f61d741bf",
    "hancoin": 300,
    "sellEndDate": "2025/04/22 20:49",
    "listingItems": [
      "A24G3",
      "AE2XV",
      "AFCJ",
      "P1118SN"
    ]
  },
  {
    "bazaarId": "a6714889b1cb46f088ffa104b62f69cc",
    "hancoin": 100,
    "sellEndDate": "2025/04/22 05:50",
    "listingItems": [
      "A453W",
      "A4ANT",
      "E1111",
      "LC1E3S"
    ]
  },
  {
    "bazaarId": "21aec614dccd425382bf786601844136",
    "hancoin": 600,
    "sellEndDate": "2025/04/20 02:02",
    "listingItems": [
      "E1Z8Q",
      "E411X0",
      "P11MH",
      "A4ABO"
    ]
  },
  {
    "bazaarId": "c2bdd96b28a24083ad3c87b42a2bbc5a",
    "hancoin": 500,
    "sellEndDate": "2025/04/20 01:44",
    "listingItems": [
      "LD212B0",
      "LD212AY",
      "P12ZHW",
      "P124LP"
    ]
  },
  {
    "bazaarId": "b48bfbe2e9ba4805af507709f3f39e84",
    "hancoin": 100,
    "sellEndDate": "2025/04/23 23:42",
    "listingItems": [
      "AF1IZ",
      "P1118XP",
      "LD111X3",
      "HD118XL"
    ]
  },
  {
    "bazaarId": "167a0372c924477d8538c577230f7242",
    "hancoin": 7500,
    "sellEndDate": "2025/04/19 16:39",
    "listingItems": [
      "B23E1"
    ]
  },
  {
    "bazaarId": "ba61f523f3854f419b2a8bf22aae6ae5",
    "hancoin": 500,
    "sellEndDate": "2025/04/23 00:33",
    "listingItems": [
      "E21DU"
    ]
  },
  {
    "bazaarId": "ef5b4d17dc3b4ab4b9eb0285bd9fafae",
    "hancoin": 8000,
    "sellEndDate": "2025/04/19 22:54",
    "listingItems": [
      "E1W4A"
    ]
  },
  {
    "bazaarId": "23f20714f448466d9571275434ec32ad",
    "hancoin": 8000,
    "sellEndDate": "2025/04/19 22:54",
    "listingItems": [
      "E41YN"
    ]
  },
  {
    "bazaarId": "89021b7072bb454c8f289b29f002f7c3",
    "hancoin": 8000,
    "sellEndDate": "2025/04/19 22:53",
    "listingItems": [
      "AA3JV"
    ]
  },
  {
    "bazaarId": "283f524d3cba4a8098c7faea7460577a",
    "hancoin": 8000,
    "sellEndDate": "2025/04/19 22:52",
    "listingItems": [
      "E21YT"
    ]
  },
  {
    "bazaarId": "1db337d394cd475fbbe68510977de0d9",
    "hancoin": 8000,
    "sellEndDate": "2025/04/19 22:51",
    "listingItems": [
      "E31V6"
    ]
  },
  {
    "bazaarId": "1d96d7a981b24ef89358841a79a249bb",
    "hancoin": 100,
    "sellEndDate": "2025/04/23 22:21",
    "listingItems": [
      "A12RL",
      "A41059",
      "B2SK",
      "P118K3"
    ]
  },
  {
    "bazaarId": "93f88abc9bbd4674b0a7c4e001a26687",
    "hancoin": 100,
    "sellEndDate": "2025/04/21 01:42",
    "listingItems": [
      "A41059"
    ]
  },
  {
    "bazaarId": "3ef491dd3399471493ea15cacdf8f7dc",
    "hancoin": 100,
    "sellEndDate": "2025/04/21 20:10",
    "listingItems": [
      "AA13T7",
      "A14E4"
    ]
  },
  {
    "bazaarId": "88d8bf41924948c3a2343ef634df0608",
    "hancoin": 300,
    "sellEndDate": "2025/04/20 10:35",
    "listingItems": [
      "LD111X3",
      "P1118SN",
      "A4D3B",
      "CT1DN"
    ]
  },
  {
    "bazaarId": "5114d83e8b244766872c4ca2188e08d5",
    "hancoin": 300,
    "sellEndDate": "2025/04/23 01:08",
    "listingItems": [
      "AB10XT",
      "B1137",
      "E31ZC",
      "A4D3B"
    ]
  },
  {
    "bazaarId": "d3e23b8c07574d40a9cf04fc20f40b33",
    "hancoin": 300,
    "sellEndDate": "2025/04/23 14:04",
    "listingItems": [
      "A4D3B",
      "LC1DVR"
    ]
  },
  {
    "bazaarId": "a0a0e7b1e3d546b4b86979ebe8afab39",
    "hancoin": 300,
    "sellEndDate": "2025/04/23 18:29",
    "listingItems": [
      "AA2UW"
    ]
  },
  {
    "bazaarId": "732f5f36012448778dbd0595ba3a6f90",
    "hancoin": 2000,
    "sellEndDate": "2025/04/23 14:12",
    "listingItems": [
      "CT2HF"
    ]
  },
  {
    "bazaarId": "2ef07c23782948019078b978afa448ba",
    "hancoin": 500,
    "sellEndDate": "2025/04/23 17:08",
    "listingItems": [
      "E213B3",
      "P1113B8"
    ]
  },
  {
    "bazaarId": "ae4db029bc114c5895d54cdaefed10b7",
    "hancoin": 1500,
    "sellEndDate": "2025/04/19 17:19",
    "listingItems": [
      "B21E2"
    ]
  },
  {
    "bazaarId": "266677c8eefa418f8364543d937c6714",
    "hancoin": 5000,
    "sellEndDate": "2025/04/19 14:05",
    "listingItems": [
      "FA2UAI"
    ]
  },
  {
    "bazaarId": "b3e5d507580f496d97028c75a8c9d17c",
    "hancoin": 4000,
    "sellEndDate": "2025/04/19 19:49",
    "listingItems": [
      "FA2UAI"
    ]
  },
  {
    "bazaarId": "9af5dea1a79a440da6e1a621766dfb60",
    "hancoin": 100,
    "sellEndDate": "2025/04/21 22:16",
    "listingItems": [
      "LC2EM7",
      "AE3T5"
    ]
  },
  {
    "bazaarId": "d2a2afced1e7401f86fee154bc5dfb6e",
    "hancoin": 100,
    "sellEndDate": "2025/04/20 03:33",
    "listingItems": [
      "AANK",
      "E1OR",
      "LC1EKJ",
      "AE19N"
    ]
  },
  {
    "bazaarId": "02ac1ed994cd4beca73254dc77d08d66",
    "hancoin": 700,
    "sellEndDate": "2025/04/19 19:22",
    "listingItems": [
      "AB440"
    ]
  },
  {
    "bazaarId": "930d42bc6072423bbd79ab2930da6522",
    "hancoin": 300,
    "sellEndDate": "2025/04/23 11:57",
    "listingItems": [
      "AA3LL"
    ]
  },
  {
    "bazaarId": "4bc58bee8ba342b2a7faf28ee7eb6272",
    "hancoin": 9500,
    "sellEndDate": "2025/04/22 13:52",
    "listingItems": [
      "A4CIM"
    ]
  },
  {
    "bazaarId": "b154bf7f37b8422ead3119862f88301d",
    "hancoin": 500,
    "sellEndDate": "2025/04/23 17:09",
    "listingItems": [
      "E3204"
    ]
  },
  {
    "bazaarId": "bd46f3a08c4d4ee4aaef2bdf8a36f4f6",
    "hancoin": 100,
    "sellEndDate": "2025/04/23 17:05",
    "listingItems": [
      "A4CVF"
    ]
  },
  {
    "bazaarId": "bbda5d6b3f1b435187626e0d79127794",
    "hancoin": 100,
    "sellEndDate": "2025/04/23 17:04",
    "listingItems": [
      "A44NE",
      "A483M",
      "A418AX",
      "A47VX"
    ]
  },
  {
    "bazaarId": "d29c1ea64b104d1dbd34c6329841db3e",
    "hancoin": 200,
    "sellEndDate": "2025/04/23 15:46",
    "listingItems": [
      "LC2EKH"
    ]
  },
  {
    "bazaarId": "d16d221b3ffe48f5ab00afe50abaa2f9",
    "hancoin": 1200,
    "sellEndDate": "2025/04/23 16:50",
    "listingItems": [
      "HD2UAK",
      "A321TP",
      "CT213TA"
    ]
  },
  {
    "bazaarId": "aca84ea184c5472d925e1a51408b2694",
    "hancoin": 5000,
    "sellEndDate": "2025/04/23 16:40",
    "listingItems": [
      "B110XU"
    ]
  },
  {
    "bazaarId": "25df6da71db6402cbda4ca8da1777969",
    "hancoin": 200,
    "sellEndDate": "2025/04/23 16:05",
    "listingItems": [
      "B329K"
    ]
  },
  {
    "bazaarId": "15b7082d2eaf4c528d8cf17ba7a07772",
    "hancoin": 200,
    "sellEndDate": "2025/04/23 16:01",
    "listingItems": [
      "LC2DPZ"
    ]
  },
  {
    "bazaarId": "69e66abefc104930b127038a362aaa0a",
    "hancoin": 200,
    "sellEndDate": "2025/04/23 15:59",
    "listingItems": [
      "LC2EMW"
    ]
  },
  {
    "bazaarId": "245e7db012d940909ed031c6ef74f529",
    "hancoin": 300,
    "sellEndDate": "2025/04/23 15:48",
    "listingItems": [
      "E21WW"
    ]
  },
  {
    "bazaarId": "20734523f63e4078bf0214ff56476486",
    "hancoin": 100,
    "sellEndDate": "2025/04/20 01:04",
    "listingItems": [
      "A4CRZ",
      "P118AB",
      "P1188O",
      "LD111X3"
    ]
  },
  {
    "bazaarId": "c1cc6b3ccfec47118a11977e9758b945",
    "hancoin": 200,
    "sellEndDate": "2025/04/23 15:20",
    "listingItems": [
      "B1WE",
      "A311OM",
      "ABTO",
      "P11IE"
    ]
  },
  {
    "bazaarId": "92446cf973c34f13a7a341628062ce23",
    "hancoin": 100,
    "sellEndDate": "2025/04/23 11:58",
    "listingItems": [
      "A44ZW",
      "ABTO",
      "LC1D2N",
      "P111ZN"
    ]
  },
  {
    "bazaarId": "6038a0cb023c437ea4050b68a779de49",
    "hancoin": 100,
    "sellEndDate": "2025/04/23 15:19",
    "listingItems": [
      "A2306",
      "LC1AUA",
      "AE19N",
      "A135H"
    ]
  },
  {
    "bazaarId": "4666d850d96c452bbb31e11179fd5ed1",
    "hancoin": 8000,
    "sellEndDate": "2025/04/23 15:01",
    "listingItems": [
      "E11KG"
    ]
  },
  {
    "bazaarId": "286b328bd353447c9d19d5cc3bf997b2",
    "hancoin": 800,
    "sellEndDate": "2025/04/19 14:13",
    "listingItems": [
      "AA3B1",
      "A263K",
      "A13C2",
      "HD118FI"
    ]
  },
  {
    "bazaarId": "5d06c8105eaf4327aa081fa45c82052f",
    "hancoin": 600,
    "sellEndDate": "2025/04/20 10:36",
    "listingItems": [
      "E11G8"
    ]
  },
  {
    "bazaarId": "223562236b944a1bb2235e967f2c91e3",
    "hancoin": 3500,
    "sellEndDate": "2025/04/19 14:05",
    "listingItems": [
      "B32EY"
    ]
  },
  {
    "bazaarId": "cfe3193e29244e7ab896bf6d936441b5",
    "hancoin": 200,
    "sellEndDate": "2025/04/20 13:59",
    "listingItems": [
      "A26DL",
      "E412UB",
      "LC1ELC"
    ]
  },
  {
    "bazaarId": "32c5d95cf42d4119a73a4dfa3e1692b8",
    "hancoin": 200,
    "sellEndDate": "2025/04/23 12:50",
    "listingItems": [
      "A48Y5",
      "CT1AW",
      "AA3P7",
      "P118AB"
    ]
  },
  {
    "bazaarId": "d6778dd0371f4107af617c1f4991ce2a",
    "hancoin": 100,
    "sellEndDate": "2025/04/23 12:00",
    "listingItems": [
      "A23JS",
      "A45A1",
      "P112Q",
      "LC1BUM"
    ]
  },
  {
    "bazaarId": "39044b46f07b4f76a67225ce7f4d0378",
    "hancoin": 4300,
    "sellEndDate": "2025/04/23 11:16",
    "listingItems": [
      "P1279Y"
    ]
  },
  {
    "bazaarId": "26bee99351e044ac8f964e74d338d13c",
    "hancoin": 4300,
    "sellEndDate": "2025/04/23 11:15",
    "listingItems": [
      "P1263N"
    ]
  },
  {
    "bazaarId": "f38f7134724e4d02b641756c44635b21",
    "hancoin": 700,
    "sellEndDate": "2025/04/23 10:58",
    "listingItems": [
      "B32DJ"
    ]
  },
  {
    "bazaarId": "0d6fffb83b9f42d1b241074335e0f8f0",
    "hancoin": 400,
    "sellEndDate": "2025/04/23 10:42",
    "listingItems": [
      "CT2FY"
    ]
  },
  {
    "bazaarId": "449e12c064bc429097ae950660583686",
    "hancoin": 200,
    "sellEndDate": "2025/04/23 10:39",
    "listingItems": [
      "P1243B"
    ]
  },
  {
    "bazaarId": "c0846e1ffac64bb7a6003117b5dc5a2f",
    "hancoin": 600,
    "sellEndDate": "2025/04/20 00:50",
    "listingItems": [
      "AA1WJ"
    ]
  },
  {
    "bazaarId": "862371b30b52400887d396ea80d5af9f",
    "hancoin": 100,
    "sellEndDate": "2025/04/19 19:18",
    "listingItems": [
      "A4C4Y",
      "LD111X3",
      "P1118SN"
    ]
  },
  {
    "bazaarId": "5b73fecfd37e40309b8eee018a0d0d70",
    "hancoin": 100,
    "sellEndDate": "2025/04/19 16:23",
    "listingItems": [
      "A13G7",
      "LC1DEZ",
      "P111HX",
      "E319O"
    ]
  },
  {
    "bazaarId": "3ec1c901ea084cd2879b3565c5a084fe",
    "hancoin": 400,
    "sellEndDate": "2025/04/23 00:34",
    "listingItems": [
      "E41CQ"
    ]
  },
  {
    "bazaarId": "eae03529fc384f7dbfd3d2e58b2a481e",
    "hancoin": 400,
    "sellEndDate": "2025/04/23 00:33",
    "listingItems": [
      "E21HR"
    ]
  },
  {
    "bazaarId": "5b16170ef645438d9f0e09f5ab87f030",
    "hancoin": 100,
    "sellEndDate": "2025/04/21 01:44",
    "listingItems": [
      "A43PB",
      "AA1AQ",
      "A13I8",
      "P11RG"
    ]
  },
  {
    "bazaarId": "3a239c91dda947659fa17935b41351e2",
    "hancoin": 200,
    "sellEndDate": "2025/04/21 23:55",
    "listingItems": [
      "AFCK",
      "P12JR",
      "AE19O",
      "A43PB"
    ]
  },
  {
    "bazaarId": "149362b1763c41bdb79b56aa50859b36",
    "hancoin": 5000,
    "sellEndDate": "2025/04/22 23:30",
    "listingItems": [
      "E222L"
    ]
  },
  {
    "bazaarId": "5eb3e46ec16a4416b9abea8a96031893",
    "hancoin": 8000,
    "sellEndDate": "2025/04/22 21:51",
    "listingItems": [
      "A15GA"
    ]
  },
  {
    "bazaarId": "bf37c1c290b54a279188277d14771ca1",
    "hancoin": 100,
    "sellEndDate": "2025/04/22 19:41",
    "listingItems": [
      "LC1D5O",
      "E223W",
      "AEHD",
      "AA1OK"
    ]
  },
  {
    "bazaarId": "789ad1b1edf6459987a6d0d8aa62925b",
    "hancoin": 100,
    "sellEndDate": "2025/04/22 21:17",
    "listingItems": [
      "AA1OK",
      "B3190"
    ]
  },
  {
    "bazaarId": "71c50a8752524507859a925bcbe9e2e8",
    "hancoin": 200,
    "sellEndDate": "2025/04/22 16:53",
    "listingItems": [
      "E1WUP",
      "P11XKZ",
      "AAX9K",
      "AAUAC"
    ]
  },
  {
    "bazaarId": "27f6eb0af8f94553ab3f476d872387a7",
    "hancoin": 300,
    "sellEndDate": "2025/04/20 10:20",
    "listingItems": [
      "P115E8",
      "AA3RE",
      "LD113TE",
      "HD118FI"
    ]
  },
  {
    "bazaarId": "f2f0db192f654cb48602c2afaaad51fc",
    "hancoin": 100,
    "sellEndDate": "2025/04/22 14:00",
    "listingItems": [
      "LC1EH5",
      "A410XS",
      "HD111LP"
    ]
  },
  {
    "bazaarId": "0c63084fef4b4647a87e954df88af7d5",
    "hancoin": 400,
    "sellEndDate": "2025/04/21 18:50",
    "listingItems": [
      "A4YII",
      "LC1ELQ",
      "B316T",
      "P1166B"
    ]
  },
  {
    "bazaarId": "57442e7f6dc7469391928250f4851343",
    "hancoin": 100,
    "sellEndDate": "2025/04/19 16:24",
    "listingItems": [
      "A4ANT",
      "P1118SN"
    ]
  },
  {
    "bazaarId": "b8c4b2ea77ba4a0987d6dc4db8e1c136",
    "hancoin": 100,
    "sellEndDate": "2025/04/21 22:17",
    "listingItems": [
      "E11K0",
      "B21L3"
    ]
  },
  {
    "bazaarId": "76aed39f920f4baaa63c3a8d54a0c969",
    "hancoin": 100,
    "sellEndDate": "2025/04/21 22:15",
    "listingItems": [
      "HD2YY0"
    ]
  },
  {
    "bazaarId": "c65f177a7c2e4988b3f68b34224d4353",
    "hancoin": 100,
    "sellEndDate": "2025/04/20 16:42",
    "listingItems": [
      "A1553"
    ]
  },
  {
    "bazaarId": "c83a8d06894a460481838e824b4dea05",
    "hancoin": 300,
    "sellEndDate": "2025/04/20 23:04",
    "listingItems": [
      "AFZHP",
      "P11ZWD",
      "LD1105H"
    ]
  },
  {
    "bazaarId": "7599c4956cfa4a3392d756c0005b7e64",
    "hancoin": 100,
    "sellEndDate": "2025/04/20 23:47",
    "listingItems": [
      "A12RG",
      "P1118SN",
      "AFZHP",
      "CT1HE"
    ]
  },
  {
    "bazaarId": "6428c12a310b4c78924aa4d66d5e64c7",
    "hancoin": 800,
    "sellEndDate": "2025/04/21 07:11",
    "listingItems": [
      "A2UAB",
      "AA2DT",
      "LC1ELS"
    ]
  },
  {
    "bazaarId": "adf1334dad064eceb6aaf2aa6682a248",
    "hancoin": 100,
    "sellEndDate": "2025/04/21 01:42",
    "listingItems": [
      "E4105E"
    ]
  },
  {
    "bazaarId": "10e09774344b4ac48cabacaff735ef75",
    "hancoin": 100,
    "sellEndDate": "2025/04/21 01:44",
    "listingItems": [
      "E4105E"
    ]
  },
  {
    "bazaarId": "895cb2a6fe2e45129bb8f6813705d540",
    "hancoin": 100,
    "sellEndDate": "2025/04/21 01:42",
    "listingItems": [
      "AAZW6"
    ]
  },
  {
    "bazaarId": "1c51c30d319341da9551afb386280376",
    "hancoin": 100,
    "sellEndDate": "2025/04/20 16:44",
    "listingItems": [
      "B2FN",
      "LC1DYW",
      "AE1JF",
      "P111U7"
    ]
  },
  {
    "bazaarId": "816b538a163a4f258c8db46819b03326",
    "hancoin": 8000,
    "sellEndDate": "2025/04/20 09:21",
    "listingItems": [
      "E211WZ"
    ]
  }
]