[
  {
    "itemCode": "AA1AI9",
    "itemName": "蜘蛛の住処",
    "parts": "AA",
    "itemGender": "A"
  },
  {
    "itemCode": "B21AMQ",
    "itemName": "マリフラ♀・s",
    "parts": "B2",
    "itemGender": "F"
  },
  {
    "itemCode": "B21AMP",
    "itemName": "マリフラ♀",
    "parts": "B2",
    "itemGender": "F"
  },
  {
    "itemCode": "LD27AI",
    "itemName": "サムライ無双",
    "parts": "HL",
    "itemGender": "F"
  },
  {
    "itemCode": "A32289",
    "itemName": "エルフ気分",
    "parts": "A3",
    "itemGender": "F"
  },
  {
    "itemCode": "A14FO",
    "itemName": "[FM＋]ハーロムピン",
    "parts": "A1",
    "itemGender": "A"
  },
  {
    "itemCode": "LD29Y8",
    "itemName": "愛の郵便ボトム",
    "parts": "HL",
    "itemGender": "F"
  },
  {
    "itemCode": "A4A2F",
    "itemName": "スターパレード",
    "parts": "A4",
    "itemGender": "A"
  },
  {
    "itemCode": "A2220",
    "itemName": "おにぎりおいしい",
    "parts": "A2",
    "itemGender": "A"
  },
  {
    "itemCode": "E2OH",
    "itemName": "ブニャティ",
    "parts": "E2",
    "itemGender": "A"
  },
  {
    "itemCode": "AAS5",
    "itemName": "ラブキュン・うーさー",
    "parts": "AA",
    "itemGender": "A"
  },
  {
    "itemCode": "A4594",
    "itemName": "ヘメラ",
    "parts": "A4",
    "itemGender": "A"
  },
  {
    "itemCode": "A4A4Y",
    "itemName": "とあるお家のお庭で",
    "parts": "A4",
    "itemGender": "A"
  },
  {
    "itemCode": "A14F1",
    "itemName": "にわとりさんだっこ",
    "parts": "A1",
    "itemGender": "A"
  },
  {
    "itemCode": "B31A3",
    "itemName": "ぴよさんと一緒",
    "parts": "B3",
    "itemGender": "M"
  },
  {
    "itemCode": "HC2BJQ",
    "itemName": "ゆるっとラグラン",
    "parts": "H",
    "itemGender": "F"
  },
  {
    "itemCode": "LC2EGL",
    "itemName": "ロリポップミニ",
    "parts": "L",
    "itemGender": "F"
  },
  {
    "itemCode": "P111262",
    "itemName": "りすくんのもふもふねぐせ",
    "parts": "P",
    "itemGender": "M"
  },
  {
    "itemCode": "LD112TU",
    "itemName": "碧玉の占い師",
    "parts": "HL",
    "itemGender": "M"
  },
  {
    "itemCode": "B28U",
    "itemName": "【パチスロＤＸ】執事タイ",
    "parts": "B2",
    "itemGender": "M"
  },
  {
    "itemCode": "AE12A",
    "itemName": "【BIG】アヤメ帽",
    "parts": "AE",
    "itemGender": "A"
  },
  {
    "itemCode": "A413A2",
    "itemName": "ヒンヤリコオリベア",
    "parts": "A4",
    "itemGender": "A"
  }
]