[
  {
    "itemCode": "FA1ZM",
    "itemName": "陽和",
    "parts": "F",
    "itemGender": "M"
  },
  {
    "itemCode": "P127OB",
    "itemName": "月凛華",
    "parts": "P",
    "itemGender": "F"
  },
  {
    "itemCode": "A4A2F",
    "itemName": "スターパレード",
    "parts": "A4",
    "itemGender": "A"
  },
  {
    "itemCode": "LD26YN",
    "itemName": "忍者がーる",
    "parts": "HL",
    "itemGender": "F"
  },
  {
    "itemCode": "LD24QH",
    "itemName": "ろぼキューピッド",
    "parts": "HL",
    "itemGender": "F"
  },
  {
    "itemCode": "LC2B6Z",
    "itemName": "ホワイトプリン服",
    "parts": "L",
    "itemGender": "F"
  },
  {
    "itemCode": "AF1BQ",
    "itemName": "イースターラビピアス",
    "parts": "AF",
    "itemGender": "A"
  },
  {
    "itemCode": "A14U4",
    "itemName": "頭のせ葉っぱ",
    "parts": "A1",
    "itemGender": "A"
  },
  {
    "itemCode": "A260O",
    "itemName": "ばっちりぬいぐるみリボン",
    "parts": "A2",
    "itemGender": "A"
  },
  {
    "itemCode": "B31A3",
    "itemName": "ぴよさんと一緒",
    "parts": "B3",
    "itemGender": "M"
  },
  {
    "itemCode": "A45X9",
    "itemName": "ぴぐモンエトランジュレーヌ",
    "parts": "A4",
    "itemGender": "A"
  },
  {
    "itemCode": "A24R5",
    "itemName": "ヨーヨー（キャンディピンク）",
    "parts": "A2",
    "itemGender": "F"
  },
  {
    "itemCode": "AE12O2",
    "itemName": "[晴]はれシニヨンキャップ・黒",
    "parts": "AE",
    "itemGender": "A"
  },
  {
    "itemCode": "AB1PB",
    "itemName": "love-evilクッション",
    "parts": "AB",
    "itemGender": "A"
  },
  {
    "itemCode": "A24CT",
    "itemName": "超接近",
    "parts": "A2",
    "itemGender": "A"
  },
  {
    "itemCode": "AD1W",
    "itemName": "ビン底メガネ",
    "parts": "AD",
    "itemGender": "M"
  },
  {
    "itemCode": "B213UZ",
    "itemName": "スノウミロワール・24th・s",
    "parts": "B2",
    "itemGender": "F"
  },
  {
    "itemCode": "B213UY",
    "itemName": "スノウミロワール・24th",
    "parts": "B2",
    "itemGender": "F"
  },
  {
    "itemCode": "LD212HE",
    "itemName": "水面ラウンジガール",
    "parts": "HL",
    "itemGender": "F"
  },
  {
    "itemCode": "AE13XH",
    "itemName": "ノアオレイユ・24th",
    "parts": "AE",
    "itemGender": "A"
  },
  {
    "itemCode": "AD13BN",
    "itemName": "グレンデザイグラス",
    "parts": "AD",
    "itemGender": "A"
  },
  {
    "itemCode": "AF1C9",
    "itemName": "耳のりしあわせの小鳥",
    "parts": "AF",
    "itemGender": "M"
  },
  {
    "itemCode": "AF19H8",
    "itemName": "モノグウスカハートピン",
    "parts": "AF",
    "itemGender": "A"
  },
  {
    "itemCode": "P125IO",
    "itemName": "メリノー",
    "parts": "P",
    "itemGender": "F"
  },
  {
    "itemCode": "P125I9",
    "itemName": "フラフィ",
    "parts": "P",
    "itemGender": "F"
  },
  {
    "itemCode": "P125K3",
    "itemName": "ほわほわツイン・ピンキー",
    "parts": "P",
    "itemGender": "F"
  }
]